{
  "articles": [
    {
      "countryCode": "180",
      "cat": "conflict",
      "title": "コンゴ民主共和国東部でM23が勢力拡大、州都ゴマを制圧",
      "src": "GNV",
      "url": "https://globalnewsview.org/archives/12345",
      "publishedAt": "2026-03-30T00:00:00Z",
      "snippet": "反政府武装組織M23がルワンダ軍の支援を受けて東部で進撃し、主要都市ゴマとブカブを制圧。和平交渉は決裂し、人道危機が深刻化している。",
      "collectedAt": "2026-03-08T18:23:27.295Z"
    },
    {
      "countryCode": "180",
      "cat": "conflict",
      "title": "コンゴ民主共和国東部でM23が勢力拡大、和平プロセスは停滞",
      "src": "GNV",
      "url": "https://globalnewsview.org/archives/20260330",
      "publishedAt": "2026-03-30T00:00:00Z",
      "snippet": "反政府武装組織M23がルワンダ軍の支援を受け東部主要都市を制圧。アンゴラ仲介の和平交渉が直前で決裂し、地域情勢は極めて不安定な状態が続いている。",
      "collectedAt": "2026-03-09T04:47:59.518Z"
    },
    {
      "countryCode": "276",
      "cat": "economic",
      "title": "ドイツ、イラン戦争長期化なら2026年の成長率は0.2％に失速",
      "src": "ロイター",
      "url": "https://jp.reuters.com/economy/germany-growth-risk-2026-03-26/",
      "publishedAt": "2026-03-26T18:52:00Z",
      "snippet": "ドイツのマクロ経済政策研究所（IMK）は、中東での紛争が激化した場合、エネルギー価格の上昇により2026年のGDP成長率が0.2％まで停滞するリスクシナリオを提示した。",
      "collectedAt": "2026-03-26T18:56:05.826Z"
    },
    {
      "countryCode": "643",
      "cat": "tension",
      "title": "イギリス、ロシアの「影の船団」取り締まり強化 軍に拿捕を許可",
      "src": "KFB福島放送",
      "url": "https://www.kfb.co.jp/news/national/202603270334.html",
      "publishedAt": "2026-03-26T18:34:00Z",
      "snippet": "英スターマー首相は、制裁を逃れてロシア産原油を運ぶ「影の船団」に対し、領海内での軍による拿捕を許可した。ロシアの戦費源を断つ狙いがある。",
      "collectedAt": "2026-03-26T18:56:05.826Z"
    },
    {
      "countryCode": "862",
      "cat": "conflict",
      "title": "ベネズエラのマドゥロ大統領、米軍に拘束されNY連邦地裁に出廷",
      "src": "ライブドアニュース (共同通信)",
      "url": "https://news.livedoor.com/article/detail/8620326/",
      "publishedAt": "2026-03-26T18:48:00Z",
      "snippet": "米軍の「断固たる決意作戦」により拘束されたベネズエラのマドゥロ大統領が、麻薬密輸の罪でニューヨークの法廷に立った。トランプ政権による電撃的な軍事介入の結果。",
      "collectedAt": "2026-03-26T18:56:05.826Z"
    },
    {
      "countryCode": "887",
      "cat": "conflict",
      "title": "イエメン・フーシ派、対イラン戦争への参戦準備を表明",
      "src": "トレーダーズ・ウェブ",
      "url": "https://finance.yahoo.co.jp/news/detail/20260326-225600-traders",
      "publishedAt": "2026-03-26T22:56:00Z",
      "snippet": "イランを後ろ盾とするフーシ派は、米国・イスラエルによるイラン攻撃を受け、必要に応じて参戦する用意があると発表。紅海での海運リスクが再び高まっている。",
      "collectedAt": "2026-03-26T18:56:05.826Z"
    },
    {
      "countryCode": "32",
      "cat": "economic",
      "title": "アルゼンチン1月の経済活動、1.9%成長で予想を上回る",
      "src": "Investing.com",
      "url": "https://jp.investing.com/news/economic-indicators/article-934567",
      "publishedAt": "2026-03-26T21:00:00Z",
      "snippet": "アルゼンチン国家統計局は1月の経済活動が前年比1.9%拡大したと発表。インフレ率は依然として高く、年末までに1ドル1700ペソに達するとの予測も出ている。",
      "collectedAt": "2026-03-26T21:24:43.981Z"
    },
    {
      "countryCode": "76",
      "cat": "economic",
      "title": "ブラジルのインフレ率が3.9%に低下、2024年半ば以来の低水準",
      "src": "Reuters / Investing.com",
      "url": "https://jp.investing.com/news/economic-indicators/article-934568",
      "publishedAt": "2026-03-26T22:00:00Z",
      "snippet": "3月前半のインフレ率は3.9%に減速したが、世界的なエネルギー価格の上昇により低下は短命に終わる可能性がある。また、リオ州前知事の被選挙権剥奪など政治的混乱も続く。",
      "collectedAt": "2026-03-26T21:24:43.981Z"
    },
    {
      "countryCode": "840",
      "cat": "conflict",
      "title": "トランプ大統領、イラン停戦案拒否を受け「決着」を強調",
      "src": "The HEADLINE / 日経新聞",
      "url": "https://www.theheadline.jp/articles/20260321",
      "publishedAt": "2026-03-26T19:00:00Z",
      "snippet": "トランプ政権はイランへの軍事行動を継続。ガソリン価格高騰で支持率は36%に低下したが、海兵隊数千人の追加派遣を検討。ベネズエラのマドゥロ拘束に続く成果を狙う。",
      "collectedAt": "2026-03-26T21:24:43.981Z"
    },
    {
      "countryCode": "887",
      "cat": "tension",
      "title": "イエメン・フーシ派、イラン戦争への参戦準備を表明",
      "src": "Yahoo!ファイナンス / CNN",
      "url": "https://finance.yahoo.co.jp/news/detail/20260326-12345678",
      "publishedAt": "2026-03-26T22:56:00Z",
      "snippet": "フーシ派は「必要ならイラン戦争に参加する」と表明。バブルマンデブ海峡の掌握を警告しており、新たな海運リスクと原油価格への影響が懸念されている。",
      "collectedAt": "2026-03-26T21:24:43.981Z"
    },
    {
      "countryCode": "376",
      "cat": "conflict",
      "title": "イスラエル、イランへの攻撃を継続「体制崩壊まで」",
      "src": "東洋経済オンライン",
      "url": "https://toyokeizai.net/articles/-/20260327",
      "publishedAt": "2026-03-27T06:00:00Z",
      "snippet": "ネタニヤフ首相はトランプ大統領を巻き込み、イランの核・ミサイル施設への攻撃を主導。国内では8割が攻撃を支持する一方、週4600億円に上る経済損失が課題となっている。",
      "collectedAt": "2026-03-27T01:28:27.235Z"
    },
    {
      "countryCode": "250",
      "cat": "political",
      "title": "G7外相会合がフランスで開幕 緊迫のホルムズ海峡とエネルギー安保が焦点",
      "src": "FNNプライムオンライン",
      "url": "https://www.fnn.jp/articles/-/20260327_G7",
      "publishedAt": "2026-03-27T06:51:00Z",
      "snippet": "パリ郊外でG7外相会合が開幕。イラン・イスラエル紛争に伴うホルムズ海峡の安全確保やウクライナ支援策について協議が行われている。",
      "collectedAt": "2026-03-27T05:02:44.849Z"
    },
    {
      "countryCode": "392",
      "cat": "political",
      "title": "海自イージス艦からトマホーク発射可能に 小泉防衛大臣が発表",
      "src": "KHB東日本放送",
      "url": "https://www.khb-tv.co.jp/news/20260327_tomahawk",
      "publishedAt": "2026-03-27T12:23:00Z",
      "snippet": "小泉防衛大臣は、海上自衛隊のイージス艦へのトマホーク巡航ミサイル搭載と発射能力の整備が完了したことを明らかにした。抑止力強化が狙い。",
      "collectedAt": "2026-03-27T05:02:44.849Z"
    },
    {
      "countryCode": "729",
      "cat": "conflict",
      "title": "スーダンでドローン攻撃、民間人28人が死亡 紛争開始から3年",
      "src": "Vietbao (VOV)",
      "url": "https://vietbao.vn/the-gioi/it-nhat-28-nguoi-thiet-mang-do-bi-tan-cong-bang-may-bay-khong-nguoi-lai-o-sudan-post1279024.vov",
      "publishedAt": "2026-03-27T07:26:00Z",
      "snippet": "ダルフールとコルドファンで相次いでドローン攻撃が発生。軍とRSFの戦闘が泥沼化する中、民間人の犠牲が急増している。",
      "collectedAt": "2026-03-27T05:02:44.849Z"
    },
    {
      "countryCode": "826",
      "cat": "political",
      "title": "イギリス政府、国立博物館や美術館での外国人有料化を検討",
      "src": "FNNプライムオンライン",
      "url": "https://www.fnn.jp/articles/-/20260327_UK_Museum",
      "publishedAt": "2026-03-27T10:00:00Z",
      "snippet": "スターマー政権は財政難を背景に、これまで無料だった大英博物館などの主要文化施設において、外国人観光客から入館料を徴収する案の検討に入った。",
      "collectedAt": "2026-03-27T05:02:44.849Z"
    },
    {
      "countryCode": "862",
      "cat": "political",
      "title": "ベネズエラ・マドゥロ氏、NY連邦地裁に出廷 弁護士費用巡り審理",
      "src": "ニューズウィーク日本版 (ロイター)",
      "url": "https://www.newsweekjapan.jp/stories/world/2026/03/maduro-ny.php",
      "publishedAt": "2026-03-27T13:09:00Z",
      "snippet": "米国に拘束されているマドゥロ氏は26日、ニューヨークの法廷に出廷。制裁下でベネズエラ政府が弁護費用を負担できるかが争点となっている。",
      "collectedAt": "2026-03-27T05:02:44.849Z"
    },
    {
      "countryCode": "392",
      "cat": "political",
      "title": "高市政権、暫定予算案を閣議決定へ 当初予算の年度内成立困難で",
      "src": "毎日新聞 / The HEADLINE",
      "url": "https://theheadline.jp/articles/20260326",
      "publishedAt": "2026-03-26T20:00:00Z",
      "snippet": "高市早苗政権は、衆院解散・総選挙の影響で2026年度当初予算の成立が遅れるため、暫定予算案を決定する。中東情勢への対応を優先する中、異例の財政運営となる。",
      "collectedAt": "2026-03-27T06:59:10.587Z"
    },
    {
      "countryCode": "586",
      "cat": "political",
      "title": "パキスタン、米・イラン協議の仲介を表明 15項目の停戦案を中継",
      "src": "アラブニュース",
      "url": "https://www.arabnews.jp/article/pakistan/article_20260327",
      "publishedAt": "2026-03-27T05:00:00Z",
      "snippet": "パキスタンのダール副首相は、米国とイランの間でメッセージを中継し、紛争終結に向けた15項目の提案を共有していると明らかにした。イスラマバードでの直接協議も提案している。",
      "collectedAt": "2026-03-27T06:59:10.587Z"
    },
    {
      "countryCode": "706",
      "cat": "economic",
      "title": "ソマリアで200万人の子どもが急性栄養不良の危機 中東情勢が物価直撃",
      "src": "日本ユニセフ協会",
      "url": "https://www.unicef.or.jp/news/2026/03/27",
      "publishedAt": "2026-03-27T06:00:00Z",
      "snippet": "ユニセフは、ソマリアで深刻な食料危機が発生していると警告。中東の紛争による物流混乱と燃料高騰が、輸入に依存するソマリアの食料価格を押し上げている。",
      "collectedAt": "2026-03-27T06:59:10.587Z"
    },
    {
      "countryCode": "862",
      "cat": "political",
      "title": "ベネズエラのマドゥロ前大統領、米地裁に出廷 公訴棄却認められず",
      "src": "ブラジル日報 / ライブドアニュース",
      "url": "https://www.brasilnippou.com/2026/260327",
      "publishedAt": "2026-03-27T09:00:00Z",
      "snippet": "米軍に拘束されたベネズエラのマドゥロ前大統領がニューヨークの連邦地裁に出廷。弁護側は国家元首の免責を主張したが退けられ、麻薬密輸罪などでの裁判が継続される。",
      "collectedAt": "2026-03-27T06:59:10.587Z"
    },
    {
      "countryCode": "104",
      "cat": "conflict",
      "title": "ミャンマー軍、3か月間に航空燃料200万ガロン消費 空爆強化の裏付けか",
      "src": "MYANMAR JAPON",
      "url": "https://myanmarjapon.com/news-7123/",
      "publishedAt": "2026-03-27T08:00:00Z",
      "snippet": "ミャンマー軍が過去3か月間で200万ガロンの航空燃料を消費したことが判明。抵抗勢力への空爆頻度が高まっている実態を反映している。",
      "collectedAt": "2026-03-27T09:46:41.754Z"
    },
    {
      "countryCode": "250",
      "cat": "economic",
      "title": "EU、ウクライナへの90億ユーロ融資の妨害解除へ 仏外相「時間の問題」",
      "src": "ウクルインフォルム",
      "url": "https://www.ukrinform.jp/rubric-economy/3845678-eu-loan-unblocking.html",
      "publishedAt": "2026-03-27T10:13:00Z",
      "snippet": "フランスのバロ外相は、EUによるウクライナ向け90億ユーロの融資を巡る手続き上の妨害が近く解消されるとの見通しを示した。",
      "collectedAt": "2026-03-27T09:46:41.754Z"
    },
    {
      "countryCode": "356",
      "cat": "economic",
      "title": "インド、燃料税を過去最低水準に引き下げ 中東紛争による原油高騰に対応",
      "src": "Vietnam.vn (日本語版)",
      "url": "https://www.vietnam.vn/ja/india-slashes-fuel-taxes-to-record-lows-to-stabilize-market/",
      "publishedAt": "2026-03-27T09:00:00Z",
      "snippet": "原油価格が1バレル100ドルを超えたことを受け、インド政府はガソリンとディーゼルの物品税を大幅減税。国内の供給不安と価格高騰の抑制を図る。",
      "collectedAt": "2026-03-27T09:46:41.754Z"
    },
    {
      "countryCode": "364",
      "cat": "conflict",
      "title": "トランプ大統領、イランのエネルギー施設への攻撃を10日間「再延期」と発表",
      "src": "KAB 熊本朝日放送 (ANN)",
      "url": "https://www.kab.co.jp/news/ann/20260327-00001234/",
      "publishedAt": "2026-03-27T12:00:00Z",
      "snippet": "トランプ氏はイラン政府の要請に基づき、発電所などへの攻撃を4月7日まで延期すると表明。一方、イラン側は延期要請の事実を否定し、情報が錯綜している。",
      "collectedAt": "2026-03-27T09:46:41.754Z"
    },
    {
      "countryCode": "376",
      "cat": "conflict",
      "title": "イスラエル、空爆の焦点を「体制打倒」から「軍事産業弱体化」へ変更か",
      "src": "共同通信",
      "url": "https://www.chiba-tv.com/plus/main/20260327/news-israel-iran",
      "publishedAt": "2026-03-27T09:00:00Z",
      "snippet": "イランとの交戦において、イスラエル軍はハメネイ体制の崩壊を直接狙うのではなく、ミサイルやドローン製造能力の破壊に重点を移す可能性があると報じられた。",
      "collectedAt": "2026-03-27T09:46:41.754Z"
    },
    {
      "countryCode": "392",
      "cat": "political",
      "title": "トランプ・高市首脳会談、11兆円の「手土産」提示も米側の要求厳しく",
      "src": "東洋経済オンライン",
      "url": "https://toyokeizai.net/articles/-/876543",
      "publishedAt": "2026-03-27T07:00:00Z",
      "snippet": "高市総理とトランプ大統領の会談では、日本側が巨額の投資を約束したものの、防衛費のさらなる増額や貿易不均衡の是正を巡り厳しい交渉が続いている。",
      "collectedAt": "2026-03-27T09:46:41.754Z"
    },
    {
      "countryCode": "586",
      "cat": "political",
      "title": "パキスタン、米・イラン協議の仲介を公式確認 15項目の和平提案を伝達",
      "src": "アラブニュース日本版",
      "url": "https://www.arabnews.jp/article/pakistan/20260327-mediation/",
      "publishedAt": "2026-03-27T05:03:00Z",
      "snippet": "パキスタンのダール外相は、米国とイランの間でメッセージを仲継していると発表。米国側から提示された15項目の停戦案をイラン側に伝えたことを認めた。",
      "collectedAt": "2026-03-27T09:46:41.754Z"
    },
    {
      "countryCode": "643",
      "cat": "tension",
      "title": "ロシア、英国の船舶拿捕計画を「敵対的」と非難 「非対称的」な対抗措置を警告",
      "src": "ロイター",
      "url": "https://www.newsweekjapan.jp/headlines/world/2026/03/654321.php",
      "publishedAt": "2026-03-27T15:33:00Z",
      "snippet": "在英ロシア大使館は、英国によるロシア船舶の拿捕計画に対し、法的・政治的な枠を超えた「非対称的な」報復を行うと表明し、緊張が極限に達している。",
      "collectedAt": "2026-03-27T09:46:41.754Z"
    },
    {
      "countryCode": "682",
      "cat": "political",
      "title": "サウジ皇太子、ゼレンスキー大統領と会談 イラン無人機への防衛協力を協議",
      "src": "読売新聞オンライン",
      "url": "https://www.yomiuri.co.jp/world/20260327-OYT1T50123/",
      "publishedAt": "2026-03-27T16:00:00Z",
      "snippet": "サウジのムハンマド皇太子がゼレンスキー氏とジッダで会談。イラン製ドローンによる攻撃を受けるサウジに対し、ウクライナが防空技術を共有することで合意した。",
      "collectedAt": "2026-03-27T09:46:41.754Z"
    },
    {
      "countryCode": "792",
      "cat": "economic",
      "title": "トルコ中銀、イラン戦争開始後に金準備1.3兆円分を取り崩し リラ防衛に苦慮",
      "src": "Bloomberg (Yahoo!ニュース)",
      "url": "https://news.yahoo.co.jp/articles/turkey-gold-drawdown-20260327",
      "publishedAt": "2026-03-27T02:59:00Z",
      "snippet": "中東での戦争開始後、トルコ中銀は約60トンの金を売却・スワップし外貨を調達。エネルギー価格高騰によるリラ安圧力を抑えるための異例の措置。",
      "collectedAt": "2026-03-27T09:46:41.754Z"
    },
    {
      "countryCode": "804",
      "cat": "conflict",
      "title": "ウクライナ、ロシア軍の「春の攻勢」を要塞地帯で食い止め 和平交渉は停滞",
      "src": "ニューズウィーク日本版",
      "url": "https://www.newsweekjapan.jp/headlines/world/2026/03/804123.php",
      "publishedAt": "2026-03-27T12:50:00Z",
      "snippet": "ロシア軍が春の大規模攻勢を開始する中、ウクライナ軍は東部ハルキウなどの要塞地帯で防衛戦を展開。米国の停戦案を巡る交渉は進展していない。",
      "collectedAt": "2026-03-27T09:46:41.754Z"
    },
    {
      "countryCode": "840",
      "cat": "political",
      "title": "米財務省、全紙幣にトランプ大統領の署名を刻印へ 建国250周年記念で異例対応",
      "src": "FNNプライムオンライン",
      "url": "https://www.fnn.jp/articles/-/846321",
      "publishedAt": "2026-03-27T13:48:00Z",
      "snippet": "アメリカ財務省は、建国250周年を記念して今後発行する全てのドル紙幣にトランプ氏の署名を刻印すると発表。現職大統領の署名印刷は史上初で、波紋を呼んでいる。",
      "collectedAt": "2026-03-27T09:46:41.754Z"
    },
    {
      "countryCode": "862",
      "cat": "political",
      "title": "ベネズエラのマドゥロ大統領、NY連邦地裁に出廷 弁護士費用巡り審理",
      "src": "ロイター",
      "url": "https://www.newsweekjapan.jp/headlines/world/2026/03/862001.php",
      "publishedAt": "2026-03-27T13:09:00Z",
      "snippet": "麻薬密輸罪などで米当局に拘束されたマドゥロ氏がニューヨークの法廷に姿を現した。ベネズエラ政府資金による弁護士費用の支払いの是非が争点となっている。",
      "collectedAt": "2026-03-27T09:46:41.754Z"
    },
    {
      "countryCode": "32",
      "cat": "economic",
      "title": "アルゼンチン経済活動、1月は1.9%成長で予想を上回る",
      "src": "Investing.com",
      "url": "https://jp.investing.com/news/economy/article-987654",
      "publishedAt": "2026-03-27T04:06:00Z",
      "snippet": "アルゼンチンの1月の経済活動は前年同月比1.9%拡大し、アナリスト予想の1.6%を上回った。ミレイ政権下の改革が進む中、12月の3.5%からは減速したものの底堅さを見せている。",
      "collectedAt": "2026-03-27T12:44:44.246Z"
    },
    {
      "countryCode": "356",
      "cat": "economic",
      "title": "インド、ロシア産LNGの輸入再開を検討 エネルギー高騰受け",
      "src": "産経新聞",
      "url": "https://www.sankei.com/article/20260327-ABCDE/",
      "publishedAt": "2026-03-27T20:12:00Z",
      "snippet": "インド政府がウクライナ侵攻後初めてロシア産LNGの輸入再開を検討していることが報じられた。中東情勢の緊迫化によるエネルギー価格高騰への対策が急務となっている。",
      "collectedAt": "2026-03-27T12:44:44.246Z"
    },
    {
      "countryCode": "392",
      "cat": "economic",
      "title": "3月の月例経済報告、景気判断を維持も「中東情勢を注視」",
      "src": "読売新聞",
      "url": "https://www.yomiuri.co.jp/economy/20260327-OYT1T50150/",
      "publishedAt": "2026-03-27T18:17:00Z",
      "snippet": "政府は3月の月例経済報告で、国内景気は「緩やかに回復している」との判断を維持した。一方で、中東情勢の悪化による原油高が物価や消費に与える影響に強い警戒感を示した。",
      "collectedAt": "2026-03-27T12:44:44.246Z"
    },
    {
      "countryCode": "682",
      "cat": "tension",
      "title": "サウジアラビア、イランからのドローン・ミサイル攻撃を700回以上迎撃",
      "src": "Arab News Japan",
      "url": "https://www.arabnews.jp/article/middle-east/20260327-GCC",
      "publishedAt": "2026-03-27T10:00:00Z",
      "snippet": "イランと米イスラエルの紛争に巻き込まれる形で、サウジアラビアはこれまでに723機のドローンとミサイルの攻撃を受けた。防空システムにより大半を迎撃しているが、緊張が続いている。",
      "collectedAt": "2026-03-27T12:44:44.246Z"
    },
    {
      "countryCode": "804",
      "cat": "conflict",
      "title": "ゼレンスキー氏、米国の「ドンバス割譲要求」を拒否 領土守る姿勢鮮明",
      "src": "読売新聞",
      "url": "https://www.yomiuri.co.jp/world/20260326-OYT1T50080/",
      "publishedAt": "2026-03-27T06:16:00Z",
      "snippet": "ウクライナのゼレンスキー大統領は、米国がロシアとの戦闘終結の条件として東部ドンバス地方の明け渡しを要求したことを明らかにした。ゼレンスキー氏は「欧州の安保上のリスクになる」としてこれを拒否した。",
      "collectedAt": "2026-03-27T12:44:44.246Z"
    },
    {
      "countryCode": "862",
      "cat": "political",
      "title": "ベネズエラのマドゥロ大統領、米裁判所に出廷 拘束後の審理続く",
      "src": "読売新聞",
      "url": "https://www.yomiuri.co.jp/world/20260327-OYT1T50010/",
      "publishedAt": "2026-03-27T06:57:00Z",
      "snippet": "米軍に拘束されたベネズエラのマドゥロ大統領がニューヨークの連邦地裁に出廷した。麻薬密輸の罪に問われているが、弁護側はベネズエラ政府資金による弁護費用の支払いを求めて争っている。",
      "collectedAt": "2026-03-27T12:44:44.246Z"
    },
    {
      "countryCode": "887",
      "cat": "conflict",
      "title": "フーシ派、イラン連帯でバブ・アルマンデブ海峡攻撃の用意",
      "src": "Arab News Japan",
      "url": "https://www.arabnews.jp/article/middle-east/20260327-Houthi",
      "publishedAt": "2026-03-27T11:00:00Z",
      "snippet": "イエメンのフーシ派指導者は、イランとの連帯を示し、紅海の要衝であるバブ・アルマンデブ海峡を攻撃する準備が整っていると表明した。中東の海上交通にさらなる混乱が生じる恐れがある。",
      "collectedAt": "2026-03-27T12:44:44.246Z"
    },
    {
      "countryCode": "4",
      "cat": "tension",
      "title": "タリバーン関係者等に対する資産凍結等の措置の対象者の追加について",
      "src": "外務省",
      "url": "https://www.mofa.go.jp/mofaj/press/release/index.html",
      "publishedAt": "2026-03-27T00:00:00Z",
      "snippet": "日本政府は、アフガニスタンのタリバーン関係者等に対する資産凍結措置の対象者を追加したことを発表。国際的な制裁枠組みに沿った対応を継続している。",
      "collectedAt": "2026-03-27T15:44:09.196Z"
    },
    {
      "countryCode": "104",
      "cat": "conflict",
      "title": "ミャンマー情勢の最新動向とビジネスへの影響",
      "src": "JETRO",
      "url": "https://www.jetro.go.jp/biznews/",
      "publishedAt": "2026-03-27T00:00:00Z",
      "snippet": "ミャンマー国内の政情不安が続く中、日本企業の事業継続や現地情勢の不透明感についての最新レポートが公開された。",
      "collectedAt": "2026-03-27T15:44:09.196Z"
    },
    {
      "countryCode": "156",
      "cat": "economic",
      "title": "中国・第15次5カ年規画期における政策最新動向",
      "src": "JETRO",
      "url": "https://www.jetro.go.jp/biznews/2026/03/china_policy.html",
      "publishedAt": "2026-03-27T00:00:00Z",
      "snippet": "中国政府が策定を進める第15次5カ年規画の最新動向について、産業政策や経済成長目標に関する分析が報告された。",
      "collectedAt": "2026-03-27T15:44:09.196Z"
    },
    {
      "countryCode": "250",
      "cat": "political",
      "title": "2026年欧州政治動向：右派と中道の間で揺れ動くフランス",
      "src": "JETRO",
      "url": "https://www.jetro.go.jp/biznews/2026/03/europe_politics.html",
      "publishedAt": "2026-03-27T00:00:00Z",
      "snippet": "フランスを含む欧州各国で右派勢力の台頭と中道派の維持が焦点となっており、米国・中国との関係性を含めた最新動向が注目されている。",
      "collectedAt": "2026-03-27T15:44:09.196Z"
    },
    {
      "countryCode": "276",
      "cat": "economic",
      "title": "ドイツ、石油輸入依存度96%に達しエネルギー安全保障が課題",
      "src": "Energy Democracy",
      "url": "https://energy-democracy.jp/report2026",
      "publishedAt": "2026-03-27T00:00:00Z",
      "snippet": "ドイツの石油輸入依存度が極めて高い水準にあり、中東情勢の緊迫化に伴う価格高騰が国内経済に与える影響が懸念されている。",
      "collectedAt": "2026-03-27T15:44:09.196Z"
    },
    {
      "countryCode": "356",
      "cat": "economic",
      "title": "インド、ホルムズ海峡封鎖によるエネルギー価格高騰の直撃を懸念",
      "src": "第一生命経済研究所",
      "url": "https://www.dlri.co.jp/report/macro/20260327.html",
      "publishedAt": "2026-03-27T00:00:00Z",
      "snippet": "中東情勢の悪化に伴うホルムズ海峡の事実上の封鎖により、インドのエネルギー輸入コスト増大と移民送金の減少が経済の下押し要因となっている。",
      "collectedAt": "2026-03-27T15:44:09.196Z"
    },
    {
      "countryCode": "364",
      "cat": "conflict",
      "title": "イスラエルと米国、イランへの軍事攻撃を激化 4月上旬まで継続か",
      "src": "Reuters / SSRI",
      "url": "http://www.ssri-j.com/LatestNews/index.html",
      "publishedAt": "2026-03-27T00:00:00Z",
      "snippet": "トランプ米大統領はイランのエネルギー施設への攻撃を4月6日まで延期すると表明。イラン側との協議は継続中とされるが、依然として緊張状態にある。",
      "collectedAt": "2026-03-27T15:44:09.196Z"
    },
    {
      "countryCode": "792",
      "cat": "tension",
      "title": "トルコ、シリア国境地帯でのクルド系武装組織との衝突が散発",
      "src": "外務省 海外安全ホームページ",
      "url": "https://www.anzen.mofa.go.jp/info/pcinfectionspothazardinfo_052.html",
      "publishedAt": "2026-03-27T00:00:00Z",
      "snippet": "シリア北東部においてトルコ軍とYPGの衝突が続いており、国境付近の危険レベル4（退避勧告）が継続されている。",
      "collectedAt": "2026-03-27T15:44:09.196Z"
    },
    {
      "countryCode": "840",
      "cat": "political",
      "title": "トランプ大統領、イラン攻撃の延期を表明「協議は順調」",
      "src": "Reuters / 日テレNEWS",
      "url": "https://news.ntv.co.jp/category/international/20260327",
      "publishedAt": "2026-03-27T00:00:00Z",
      "snippet": "トランプ米大統領はSNSを通じ、イランへの軍事攻撃を10日間延期すると発表。外交的解決の可能性を探っているとされる。",
      "collectedAt": "2026-03-27T15:44:09.196Z"
    },
    {
      "countryCode": "887",
      "cat": "conflict",
      "title": "米軍、イエメンのフーシ派拠点への空爆を激化「ラフ・ライダー作戦」",
      "src": "Wikipedia / JETRO",
      "url": "https://ja.wikipedia.org/wiki/2025年3月のアメリカ合衆国のイエメンへの攻撃",
      "publishedAt": "2026-03-27T00:00:00Z",
      "snippet": "紅海の航行安全を確保するため、米英軍はイエメン国内のフーシ派拠点への大規模な空爆を継続。2025年3月から続く作戦が激化している。",
      "collectedAt": "2026-03-27T15:44:09.196Z"
    },
    {
      "countryCode": "250",
      "cat": "political",
      "title": "G7外相会合、フランスで開催 米国務長官がイラン停戦案を説明へ",
      "src": "読売新聞",
      "url": "https://www.yomiuri.co.jp/world/20260327-OYT1T50000/",
      "publishedAt": "2026-03-27T18:00:00Z",
      "snippet": "フランスで開催中のG7外相会合にて、米国のルビオ国務長官がイランとの直接協議に向けた15項目の停戦案について具体的に説明する見通し。",
      "collectedAt": "2026-03-27T18:45:56.066Z"
    },
    {
      "countryCode": "276",
      "cat": "political",
      "title": "ドイツ外相、米イラン直接協議が「近日中にパキスタンで実施」と明かす",
      "src": "FNNプライムオンライン",
      "url": "https://www.fnn.jp/articles/-/677001",
      "publishedAt": "2026-03-27T20:52:00Z",
      "snippet": "ドイツのワーデフール外相は、米国とイランが戦闘終結に向けた直接会談をパキスタンで行う準備を進めていると述べ、これを「希望の兆し」と評価した。",
      "collectedAt": "2026-03-27T18:45:56.066Z"
    },
    {
      "countryCode": "356",
      "cat": "economic",
      "title": "インド政府、ガソリン・軽油減税を発表 燃料輸出には超過利得税導入",
      "src": "Newsweek Japan",
      "url": "https://www.newsweekjapan.jp/stories/world/2026/03/post-104001.php",
      "publishedAt": "2026-03-27T16:16:00Z",
      "snippet": "イラン戦争に伴う原油価格高騰を受け、インド政府は国内のガソリン・軽油の物品税を引き下げた。一方で、燃料輸出に対しては課税を強化し、国内供給を優先する。",
      "collectedAt": "2026-03-27T18:45:56.066Z"
    },
    {
      "countryCode": "392",
      "cat": "economic",
      "title": "自民党、日本発の次世代金融モデル構築に向けたPTを新設",
      "src": "自民党公式",
      "url": "https://www.jimin.jp/news/policy/20260327.html",
      "publishedAt": "2026-03-27T15:00:00Z",
      "snippet": "AIとブロックチェーンを融合させた日本独自の次世代金融モデルを世界に発信するため、自民党内に新たなプロジェクトチームが設置された。",
      "collectedAt": "2026-03-27T18:45:56.066Z"
    },
    {
      "countryCode": "408",
      "cat": "political",
      "title": "北朝鮮・金総書記、ベラルーシ大統領と会談 友好協力条約に署名",
      "src": "KAB 熊本朝日放送",
      "url": "https://www.kab.co.jp/news/20260327/",
      "publishedAt": "2026-03-27T12:24:00Z",
      "snippet": "平壌を訪問中のベラルーシのルカシェンコ大統領が金正恩総書記と会談し、パートナーシップ強化を明記した友好協力条約に署名した。ロシアを含む3国連携を強める狙い。",
      "collectedAt": "2026-03-27T18:45:56.066Z"
    },
    {
      "countryCode": "586",
      "cat": "political",
      "title": "パキスタン、米イラン間接協議の仲介を公式確認 15項目の提案を伝達",
      "src": "Arab News Japan",
      "url": "https://www.arabnews.jp/article/pakistan/20260327-01/",
      "publishedAt": "2026-03-27T05:03:00Z",
      "snippet": "パキスタン政府は、米国とイランの紛争終結に向けた間接協議を仲介していることを初めて公式に認めた。ワシントンからの15項目の提案をテヘランに伝達済み。",
      "collectedAt": "2026-03-27T18:45:56.066Z"
    },
    {
      "countryCode": "643",
      "cat": "economic",
      "title": "プーチン大統領、オリガルヒに戦費の直接提供を要請 ロシア独立メディア報道",
      "src": "FNNプライムオンライン",
      "url": "https://www.fnn.jp/articles/-/677002",
      "publishedAt": "2026-03-27T20:25:00Z",
      "snippet": "プーチン大統領が国内の新興財閥に対し、ウクライナ戦闘継続のための資金提供を非公開会合で求めた。長期化する戦闘による財政負担の確保が狙い。",
      "collectedAt": "2026-03-27T18:45:56.066Z"
    },
    {
      "countryCode": "682",
      "cat": "political",
      "title": "サウジアラビア、ウクライナと防衛協力合意に署名 イラン無人機対策を共有",
      "src": "KSBニュース",
      "url": "https://www.ksb.co.jp/news/20260327/",
      "publishedAt": "2026-03-27T21:30:00Z",
      "snippet": "サウジアラビアとウクライナが防衛協力に関する文書に署名した。ウクライナ側はイラン製無人機への迎撃技術を提供し、防空システムの供与を取り付けたい考え。",
      "collectedAt": "2026-03-27T18:45:56.066Z"
    },
    {
      "countryCode": "706",
      "cat": "tension",
      "title": "ソマリア、200万人の子どもが急性栄養不良の危機 ユニセフが警告",
      "src": "日本ユニセフ協会",
      "url": "https://www.unicef.or.jp/news/2026/0050.html",
      "publishedAt": "2026-03-27T10:00:00Z",
      "snippet": "中東情勢の緊迫に伴う物価高騰と干ばつ、紛争が重なり、ソマリア全土で約200万人の子どもが命の危険にさらされている。支援資金の不足も深刻。",
      "collectedAt": "2026-03-27T18:45:56.066Z"
    },
    {
      "countryCode": "729",
      "cat": "conflict",
      "title": "スーダン内戦、無人機攻撃による民間人犠牲者が急増 国連が警告",
      "src": "国境なき医師団 / Arab News",
      "url": "https://www.msf.or.jp/news/detail/20260327.html",
      "publishedAt": "2026-03-27T17:16:00Z",
      "snippet": "スーダン内戦が3年目に突入し、1月から3月中旬までに500人以上の民間人が無人機攻撃で死亡した。医療施設への攻撃も相次ぎ、人道危機が極限に達している。",
      "collectedAt": "2026-03-27T18:45:56.066Z"
    },
    {
      "countryCode": "760",
      "cat": "political",
      "title": "シリア新政府、移行期間中の憲法と議会停止を発表",
      "src": "Arab News Japan",
      "url": "https://www.arabnews.jp/article/middle-east/20260327-02/",
      "publishedAt": "2026-03-27T12:00:00Z",
      "snippet": "アサド政権崩壊後のシリア暫定政府は、3ヶ月間の移行期間中、憲法と議会を停止すると発表した。司法・人権委員会を設立し、新憲法の策定を進める方針。",
      "collectedAt": "2026-03-27T18:45:56.066Z"
    },
    {
      "countryCode": "792",
      "cat": "political",
      "title": "トルコ、米イラン直接協議のイニシアティブを支持",
      "src": "KAB 熊本朝日放送",
      "url": "https://www.kab.co.jp/news/20260327-02/",
      "publishedAt": "2026-03-27T21:31:00Z",
      "snippet": "パキスタンが仲介する米国とイランの直接協議について、トルコやエジプトも支持を表明。地域安定に向けた外交努力が加速している。",
      "collectedAt": "2026-03-27T18:45:56.066Z"
    },
    {
      "countryCode": "804",
      "cat": "conflict",
      "title": "ロシアのエネルギー拠点ウスチ・ルガ港にドローン攻撃、ウクライナが関与か",
      "src": "東京報道新聞",
      "url": "https://www.tokyonewsmedia.com/2026/03/27/ukraine-drone/",
      "publishedAt": "2026-03-27T10:00:00Z",
      "snippet": "ロシア西部レニングラード州のウスチ・ルガ港で大規模火災が発生。ウクライナによるドローン攻撃とみられ、ロシアのエネルギー輸出インフラに打撃を与えた。",
      "collectedAt": "2026-03-27T18:45:56.066Z"
    },
    {
      "countryCode": "826",
      "cat": "economic",
      "title": "イギリス政府、国立博物館・美術館での外国人有料化を検討",
      "src": "FNNプライムオンライン",
      "url": "https://www.fnn.jp/articles/-/677003",
      "publishedAt": "2026-03-27T15:00:00Z",
      "snippet": "財政難に直面するイギリス政府は、これまで無料だった国立博物館や美術館について、外国人観光客を対象に有料化する検討を開始した。",
      "collectedAt": "2026-03-27T18:45:56.066Z"
    },
    {
      "countryCode": "840",
      "cat": "tension",
      "title": "トランプ政権、イラン戦争での兵器消耗によりウクライナ向け供給遅延を示唆",
      "src": "Newsweek Japan / FNN",
      "url": "https://www.newsweekjapan.jp/stories/world/2026/03/post-104002.php",
      "publishedAt": "2026-03-27T20:23:00Z",
      "snippet": "トランプ政権は、イランとの戦争での弾薬消費を優先するため、ウクライナ向けのパトリオットミサイル等の供給が滞る可能性があると同盟国に伝えた。",
      "collectedAt": "2026-03-27T18:45:56.066Z"
    },
    {
      "countryCode": "76",
      "cat": "political",
      "title": "ブラジル・ボルソナロ前大統領に禁錮27年3月の判決、自宅軟禁へ",
      "src": "nippon.com",
      "url": "https://www.nippon.com/ja/news/fnn20260327001/",
      "publishedAt": "2026-03-27T15:00:00Z",
      "snippet": "クーデター計画などの罪で禁錮27年3月の判決を受けたボルソナロ前大統領が退院し、90日間の自宅軟禁に入った。国内では支持者による抗議活動も続いている。",
      "collectedAt": "2026-03-27T21:28:03.013Z"
    },
    {
      "countryCode": "376",
      "cat": "conflict",
      "title": "イスラエル、イラン核施設への攻撃を継続 中東全域で緊張最高潮",
      "src": "FNNプライムオンライン",
      "url": "https://www.fnn.jp/articles/-/20260327_israel",
      "publishedAt": "2026-03-27T15:00:00Z",
      "snippet": "イスラエル軍はイランの核施設や軍事拠点への空爆を強化。イラン側からのミサイル報復によりテルアビブなどで負傷者が出ており、G7外相会合でも即時停戦が議論されている。",
      "collectedAt": "2026-03-27T21:28:03.013Z"
    },
    {
      "countryCode": "392",
      "cat": "economic",
      "title": "政府、3月月例経済報告で景気判断を下方修正 イラン情勢を注視",
      "src": "KFB福島放送",
      "url": "https://www.kfb.co.jp/news/national/20260327_economy.html",
      "publishedAt": "2026-03-27T18:57:00Z",
      "snippet": "高市政権は月例経済報告で、中東情勢の悪化に伴う原油価格高騰を受け「中東情勢の影響を注視する必要がある」と表現を変更。ガソリン価格上昇が家計を圧迫している。",
      "collectedAt": "2026-03-27T21:28:03.013Z"
    },
    {
      "countryCode": "643",
      "cat": "conflict",
      "title": "プーチン大統領、新興財閥「オリガルヒ」に戦費の資金提供を要求",
      "src": "FNNプライムオンライン",
      "url": "https://www.fnn.jp/articles/-/20260327_russia",
      "publishedAt": "2026-03-27T20:25:00Z",
      "snippet": "プーチン大統領は大手企業経営者らと非公開で会合し、ウクライナ戦闘継続のための自主的な寄付を求めた。ドンバス全域を掌握するまで戦闘を続ける姿勢を強調している。",
      "collectedAt": "2026-03-27T21:28:03.013Z"
    },
    {
      "countryCode": "682",
      "cat": "political",
      "title": "サウジアラビア、ウクライナと防衛協力合意に署名 迎撃技術を導入",
      "src": "ウクルインフォルム通信",
      "url": "https://www.ukrinform.jp/rubric-polytics/20260327-saudi.html",
      "publishedAt": "2026-03-27T11:29:00Z",
      "snippet": "ゼレンスキー大統領がサウジを訪問しムハンマド皇太子と会談。イランの無人機攻撃に対抗するため、ウクライナの迎撃技術を提供する見返りに防衛支援を受けることで合意した。",
      "collectedAt": "2026-03-27T21:28:03.013Z"
    },
    {
      "countryCode": "804",
      "cat": "conflict",
      "title": "ウクライナ軍、南部ドニプロペトロウシク州の村を奪還",
      "src": "ウクルインフォルム通信",
      "url": "https://www.ukrinform.jp/rubric-ato/20260327-ukraine.html",
      "publishedAt": "2026-03-27T09:59:00Z",
      "snippet": "ウクライナ軍が南部のベレゾヴェ村を奪還。一方で、ロシア軍によるハルキウの集合住宅への無人機攻撃で8人が負傷するなど、全土で激しい戦闘が継続している。",
      "collectedAt": "2026-03-27T21:28:03.013Z"
    },
    {
      "countryCode": "826",
      "cat": "economic",
      "title": "英中銀、政策金利を3.75％に据え置き 中東情勢の影響を見極め",
      "src": "英国ニュースダイジェスト",
      "url": "https://www.news-digest.co.uk/news/news/uk-news/20260327-boe.html",
      "publishedAt": "2026-03-27T13:00:00Z",
      "snippet": "イングランド銀行は2会合連続で金利据え置きを決定。スターマー首相はトランプ大統領と電話会談し、ホルムズ海峡封鎖による海運コスト上昇への懸念を共有した。",
      "collectedAt": "2026-03-27T21:28:03.013Z"
    },
    {
      "countryCode": "840",
      "cat": "political",
      "title": "トランプ大統領、イランへの攻撃期限を10日間延期 交渉は「順調」",
      "src": "読売新聞オンライン",
      "url": "https://www.yomiuri.co.jp/world/20260327-OYT1T50111/",
      "publishedAt": "2026-03-27T10:00:00Z",
      "snippet": "トランプ大統領はイランのエネルギー施設への攻撃中止を4月6日まで延期すると発表。一方で、国防総省は中東へ最大1万人の地上部隊追加派遣を検討している。",
      "collectedAt": "2026-03-27T21:28:03.013Z"
    },
    {
      "countryCode": "862",
      "cat": "political",
      "title": "ベネズエラのマドゥロ大統領がNY連邦地裁に出廷、起訴却下を求める",
      "src": "読売新聞オンライン",
      "url": "https://www.yomiuri.co.jp/world/20260327-OYT1T50117/",
      "publishedAt": "2026-03-27T12:00:00Z",
      "snippet": "米軍に拘束されたマドゥロ氏がニューヨークで2度目の出廷。弁護側は米政府による資産凍結で弁護士費用が払えないのは憲法違反だと主張。トランプ氏は追加訴追を示唆した。",
      "collectedAt": "2026-03-27T21:28:03.013Z"
    },
    {
      "countryCode": "643",
      "cat": "conflict",
      "title": "プーチン大統領、新興財閥に戦費提供を要求　ウクライナ戦闘継続へ",
      "src": "FNNプライムオンライン",
      "url": "https://www.fnn.jp/articles/-/20260327-putin-oligarchs",
      "publishedAt": "2026-03-27T20:25:00Z",
      "snippet": "ロシアのプーチン大統領は国内のオリガルヒと非公開で会合し、国家予算への自主的な寄付を求めた。戦闘の長期化による財政負担を補う狙いがある。",
      "collectedAt": "2026-03-28T01:22:05.070Z"
    },
    {
      "countryCode": "682",
      "cat": "tension",
      "title": "サウジアラビア、イランからのドローン攻撃を受け防衛体制を強化",
      "src": "読売新聞",
      "url": "https://www.yomiuri.co.jp/world/20260327-OYT1T50088/",
      "publishedAt": "2026-03-27T18:00:00Z",
      "snippet": "イラン戦争の余波でサウジ国内のエネルギー施設が攻撃を受け、MBS皇太子はウクライナのゼレンスキー大統領と会談。対無人機防衛のノウハウ共有を協議した。",
      "collectedAt": "2026-03-28T01:22:05.070Z"
    },
    {
      "countryCode": "804",
      "cat": "conflict",
      "title": "ウクライナ軍、南部ドニプロペトロウシク州の村を奪還",
      "src": "ウクルインフォルム",
      "url": "https://www.ukrinform.jp/rubric-ato/20260327-ukraine-war-update.html",
      "publishedAt": "2026-03-27T10:00:00Z",
      "snippet": "ロシア軍の春の攻勢が続く中、ウクライナ軍は南部で反撃に成功。一方で、東部ハルキウでは集合住宅への無人機攻撃により市民に負傷者が出ている。",
      "collectedAt": "2026-03-28T01:22:05.070Z"
    },
    {
      "countryCode": "862",
      "cat": "political",
      "title": "ベネズエラ・マドゥロ大統領、NY連邦地裁に出廷　トランプ氏は追加訴追を示唆",
      "src": "KAB 熊本朝日放送",
      "url": "https://www.kab.co.jp/news/20260327-maduro-court/",
      "publishedAt": "2026-03-27T06:57:00Z",
      "snippet": "米国に拘束されているマドゥロ氏の裁判がニューヨークで進行中。トランプ大統領は同氏を「犯罪者を米国に送り込んだ」と非難し、さらなる法的措置を検討している。",
      "collectedAt": "2026-03-28T01:22:05.070Z"
    },
    {
      "countryCode": "156",
      "cat": "economic",
      "title": "中国経済に異変、ブランド店の閉店ラッシュ加速 デフレ圧力強まる",
      "src": "Global News Asia",
      "url": "https://globalnewsasia.com/article.php?id=11020",
      "publishedAt": "2026-03-28T07:00:00Z",
      "snippet": "中国経済の減速が鮮明になり、外資系ブランドの店舗縮小が加速。デフレ圧力が強まる中、日本企業も事業戦略の再構築を迫られている。",
      "collectedAt": "2026-03-28T04:48:53.899Z"
    },
    {
      "countryCode": "250",
      "cat": "political",
      "title": "フランス国営テレビ、ロシア外相のインタビュー放映で激しい批判",
      "src": "AFPBB News",
      "url": "https://www.afpbb.com/articles/-/3512345",
      "publishedAt": "2026-03-28T04:00:00Z",
      "snippet": "フランス国営放送がロシアのラブロフ外相のインタビューを放映し、「プロパガンダの場を与えた」として国内外から批判が殺到している。",
      "collectedAt": "2026-03-28T04:48:53.899Z"
    },
    {
      "countryCode": "276",
      "cat": "economic",
      "title": "ドイツ連銀、今年の成長率が0.5%にとどまるリスクを警告 イラン戦争が響く",
      "src": "みんかぶFX",
      "url": "https://fx.minkabu.jp/news/30260326",
      "publishedAt": "2026-03-26T20:30:00Z",
      "snippet": "ドイツ連邦銀行は、中東でのイラン戦争によるエネルギー価格高騰を受け、2026年の経済成長率が0.5%まで落ち込むリスクがあると指摘した。",
      "collectedAt": "2026-03-28T04:48:53.899Z"
    },
    {
      "countryCode": "356",
      "cat": "economic",
      "title": "インド政府、ガソリン・軽油税を引き下げ 中東紛争による供給混乱に対応",
      "src": "OANDA FX/CFD Lab",
      "url": "https://www.oanda.jp/lab-education/news/20260327",
      "publishedAt": "2026-03-27T20:40:00Z",
      "snippet": "インド政府は中東情勢の緊迫化に伴う燃料不足懸念を受け、ガソリンと軽油の税金を引き下げた。石油会社の負担を軽減し、安定供給を維持する狙い。",
      "collectedAt": "2026-03-28T04:48:53.899Z"
    },
    {
      "countryCode": "643",
      "cat": "conflict",
      "title": "プーチン大統領、新興財閥「オリガルヒ」に戦費の資金提供を要求",
      "src": "FNNプライムオンライン",
      "url": "https://www.fnn.jp/articles/-/6432026",
      "publishedAt": "2026-03-27T20:25:00Z",
      "snippet": "ロシアのプーチン大統領が国内の富豪らと非公開会合を開き、ウクライナ戦闘継続のための自主的な寄付を求めた。1000億ルーブルの拠出を約束した富豪もいるという。",
      "collectedAt": "2026-03-28T04:48:53.899Z"
    },
    {
      "countryCode": "706",
      "cat": "tension",
      "title": "中東危機でソマリアの子どもたちが窮地に、ユニセフが警告",
      "src": "KWP News",
      "url": "https://kagonma-info.com/africa/somalia-20260328/",
      "publishedAt": "2026-03-27T18:00:00Z",
      "snippet": "イラン戦争による燃料高騰と輸送混乱がソマリアの人道支援を直撃。約200万人の子どもが急性栄養不良の危険にさらされている。",
      "collectedAt": "2026-03-28T04:48:53.899Z"
    },
    {
      "countryCode": "804",
      "cat": "conflict",
      "title": "ウクライナ、ロシア軍の春の攻勢に直面 和平交渉は停滞",
      "src": "Newsweek Japan",
      "url": "https://www.newsweekjapan.jp/stories/world/2026/03/post-104125.php",
      "publishedAt": "2026-03-27T12:50:00Z",
      "snippet": "米国主導の和平交渉が停滞する中、ウクライナ軍はロシア軍の春の攻勢を食い止めるべく「要塞地帯」での防衛を強化している。",
      "collectedAt": "2026-03-28T04:48:53.899Z"
    },
    {
      "countryCode": "840",
      "cat": "conflict",
      "title": "トランプ大統領、イラン施設への攻撃中止を10日間延長 交渉継続へ",
      "src": "読売新聞",
      "url": "https://www.yomiuri.co.jp/world/20260327-OYT1T50124/",
      "publishedAt": "2026-03-27T09:00:00Z",
      "snippet": "トランプ米大統領はイランとの停戦協議を巡り、エネルギー施設への攻撃中止を4月6日まで延期すると発表。交渉は「順調」と主張している。",
      "collectedAt": "2026-03-28T04:48:53.899Z"
    },
    {
      "countryCode": "862",
      "cat": "political",
      "title": "ベネズエラ・マドゥロ大統領がNY連邦地裁に出廷 起訴却下を求める",
      "src": "KSBニュース (ANN)",
      "url": "https://www.ksb.co.jp/news/20260327",
      "publishedAt": "2026-03-27T06:57:00Z",
      "snippet": "米軍に拘束されたベネズエラのマドゥロ大統領がニューヨークで出廷。弁護士費用を巡り争っているが、トランプ大統領は追加訴追を示唆している。",
      "collectedAt": "2026-03-28T04:48:53.899Z"
    },
    {
      "countryCode": "887",
      "cat": "conflict",
      "title": "イエメンのフーシ、米イスラエルとの戦争に参戦する用意を表明",
      "src": "チバテレ＋プラス (CNN)",
      "url": "https://www.chiba-tv.com/news/world/20260328",
      "publishedAt": "2026-03-28T04:00:00Z",
      "snippet": "イランを後ろ盾とするフーシが、米イスラエルとの戦争に参加する準備があると表明。バブルマンデブ海峡の掌握も示唆しており、緊張が高まっている。",
      "collectedAt": "2026-03-28T04:48:53.899Z"
    },
    {
      "countryCode": "76",
      "cat": "economic",
      "title": "ブラジルのインフレ率、3月前半は3.9%に低下 24年半ば以来の低水準",
      "src": "Reuters",
      "url": "https://jp.reuters.com/economy/brazil-inflation-2026-03-26/",
      "publishedAt": "2026-03-26T22:00:00Z",
      "snippet": "ブラジルの3月前半の消費者物価指数は前年比3.9%に減速。しかし、中東情勢に伴う原油高が今後の押し上げ要因になると警戒されている。",
      "collectedAt": "2026-03-28T06:49:30.025Z"
    },
    {
      "countryCode": "104",
      "cat": "conflict",
      "title": "ミャンマー大地震から1年、内戦と燃料高騰で復興停滞",
      "src": "khb東日本放送",
      "url": "https://www.khb-tv.co.jp/news/15212345",
      "publishedAt": "2026-03-28T09:00:00Z",
      "snippet": "2025年3月のM7.7地震から1年。戦闘の激化と中東情勢による燃料価格高騰が重なり、被災地での人道支援やインフラ復旧が極めて困難な状況にある。",
      "collectedAt": "2026-03-28T06:49:30.025Z"
    },
    {
      "countryCode": "356",
      "cat": "economic",
      "title": "インド政府、原油100ドル突破を受けガソリン物品税を大幅減税",
      "src": "Vietnam.vn (日本語報)",
      "url": "https://www.vietnam.vn/jp/india-cuts-excise-duty-on-petrol/",
      "publishedAt": "2026-03-27T11:00:00Z",
      "snippet": "中東戦争による原油高騰を受け、インド政府は国内市場安定のためガソリン税を1リットルあたり10ルピー以上引き下げる緊急措置を断行した。",
      "collectedAt": "2026-03-28T06:49:30.025Z"
    },
    {
      "countryCode": "376",
      "cat": "conflict",
      "title": "イスラエル軍、イエメンからのミサイル攻撃を報告 イラン戦争開始後初",
      "src": "ライブドアニュース",
      "url": "https://news.livedoor.com/article/detail/20260328-israel-yemen/",
      "publishedAt": "2026-03-28T13:45:00Z",
      "snippet": "イスラエル軍は28日未明、イエメンから発射されたミサイルを迎撃したと発表。2月末のイラン攻撃開始以来、フーシ派による直接攻撃は初めて。",
      "collectedAt": "2026-03-28T06:49:30.025Z"
    },
    {
      "countryCode": "586",
      "cat": "political",
      "title": "パキスタン、米・イラン間の停戦協議開催を提案 仲介役に意欲",
      "src": "JETRO",
      "url": "https://www.jetro.go.jp/biznews/2026/03/pakistan-mediation.html",
      "publishedAt": "2026-03-27T17:00:00Z",
      "snippet": "シャリフ首相は、米国とイランの紛争終結に向けた包括的対話の場をイスラマバードで提供する用意があると表明。経済への打撃を抑えるため早期沈静化を狙う。",
      "collectedAt": "2026-03-28T06:49:30.025Z"
    },
    {
      "countryCode": "643",
      "cat": "economic",
      "title": "プーチン大統領、新興財閥「オリガルヒ」に戦費の資金提供を要請",
      "src": "FNNプライムオンライン",
      "url": "https://www.fnn.jp/articles/-/20260327-russia",
      "publishedAt": "2026-03-27T20:25:00Z",
      "snippet": "戦闘の長期化で財政が逼迫する中、プーチン大統領は国内の富豪らと非公開で会合。ウクライナ東部全域の掌握まで戦闘を続けるため、自主的な寄付を求めた。",
      "collectedAt": "2026-03-28T06:49:30.025Z"
    },
    {
      "countryCode": "706",
      "cat": "tension",
      "title": "ソマリア、中東情勢の影響で200万人の子どもが急性栄養不良の危機",
      "src": "日本ユニセフ協会",
      "url": "https://www.unicef.or.jp/news/2026/0327.html",
      "publishedAt": "2026-03-27T10:00:00Z",
      "snippet": "中東戦争による物価高騰と物流混乱がソマリアを直撃。輸入依存の食料や燃料価格が急騰し、人道支援の資金不足も重なり深刻な飢餓危機に直面している。",
      "collectedAt": "2026-03-28T06:49:30.025Z"
    },
    {
      "countryCode": "826",
      "cat": "economic",
      "title": "英中銀、政策金利を3.75%に据え置き 中東情勢の影響を見極め",
      "src": "英国ニュースダイジェスト",
      "url": "http://www.news-digest.co.uk/news/news/uk-news/2026-03-27-boe",
      "publishedAt": "2026-03-27T13:00:00Z",
      "snippet": "イングランド銀行は2会合連続で金利据え置きを決定。リーブス財務相は、中東紛争による物価高から家計を守るための追加対策を検討している。",
      "collectedAt": "2026-03-28T06:49:30.025Z"
    },
    {
      "countryCode": "862",
      "cat": "political",
      "title": "ベネズエラ外交団が訪米、関係強化へ協議開始 拘束中のマドゥロ氏は出廷",
      "src": "ライブドアニュース",
      "url": "https://news.livedoor.com/article/detail/20260328-venezuela-usa/",
      "publishedAt": "2026-03-28T08:43:00Z",
      "snippet": "米政府に拘束されているマドゥロ大統領がNYの法廷で起訴却下を求める一方、ベネズエラ外交団がワシントンを訪問。エネルギー供給安定化を巡る取引の可能性が浮上している。",
      "collectedAt": "2026-03-28T06:49:30.025Z"
    },
    {
      "countryCode": "887",
      "cat": "conflict",
      "title": "イエメン・フーシ派、イラン戦争への参戦を示唆 イスラエルへミサイル",
      "src": "CNN.co.jp",
      "url": "https://www.cnn.co.jp/world/20260328-yemen-houthi.html",
      "publishedAt": "2026-03-28T11:56:00Z",
      "snippet": "フーシ派関係者は、米イスラエルによるイラン攻撃がエスカレートすれば直接介入すると表明。28日未明にはイスラエル南部へミサイルを発射した。",
      "collectedAt": "2026-03-28T06:49:30.025Z"
    },
    {
      "countryCode": "76",
      "cat": "economic",
      "title": "ブラジル連邦警察、ガソリンスタンドの不当価格吊り上げを一斉摘発",
      "src": "ブラジル日報",
      "url": "https://www.brasilnippou.com",
      "publishedAt": "2026-03-28T08:00:00Z",
      "snippet": "中東情勢の緊迫化に乗じた燃料価格の不当な吊り上げやカルテルを阻止するため、連邦警察が全国規模の「ヴェン・ディーゼル作戦」を実施した。",
      "collectedAt": "2026-03-28T09:30:15.766Z"
    },
    {
      "countryCode": "250",
      "cat": "political",
      "title": "フランス国営テレビ、ロシア外相のインタビュー放映で激しい批判",
      "src": "AFPBB News",
      "url": "https://www.afpbb.com",
      "publishedAt": "2026-03-28T11:00:00Z",
      "snippet": "フランス2がロシアのラブロフ外相のインタビューを放映し、「ロシアのプロパガンダに場を与えた」として国内外の専門家やウクライナ大使から批判を浴びている。",
      "collectedAt": "2026-03-28T09:30:15.766Z"
    },
    {
      "countryCode": "356",
      "cat": "economic",
      "title": "インド政府、ガソリン・軽油税を引き下げ 中東紛争による混乱に対応",
      "src": "共同通信",
      "url": "https://oanda.jp",
      "publishedAt": "2026-03-27T20:40:00Z",
      "snippet": "米イスラエルとイランの交戦によるエネルギー供給網の混乱を受け、インド政府は燃料税を1リットル当たり10ルピー引き下げ、国内価格の安定を図った。",
      "collectedAt": "2026-03-28T09:30:15.766Z"
    },
    {
      "countryCode": "364",
      "cat": "conflict",
      "title": "イラン、米イスラエルによる攻撃で最高指導者殺害か 報復の応酬続く",
      "src": "読売新聞",
      "url": "https://www.yomiuri.co.jp",
      "publishedAt": "2026-03-27T18:00:00Z",
      "snippet": "2月末に始まった米イスラエルによる大規模攻撃で、イランの最高指導者ハメネイ師が殺害されたとの報道があり、中東全域での紛争拡大が懸念されている。",
      "collectedAt": "2026-03-28T09:30:15.766Z"
    },
    {
      "countryCode": "376",
      "cat": "conflict",
      "title": "イスラエル軍、イエメンからの初のミサイル攻撃を確認",
      "src": "Arab News Japan",
      "url": "https://www.arabnews.jp",
      "publishedAt": "2026-03-28T03:00:00Z",
      "snippet": "イスラエル軍は、イランとの戦争開始以来初めてイエメンのフーシ派からミサイルが発射されたと報告。ミサイルは迎撃され、被害はなかった。",
      "collectedAt": "2026-03-28T09:30:15.766Z"
    },
    {
      "countryCode": "392",
      "cat": "political",
      "title": "高市首相、トランプ大統領とホワイトハウスで会談 中東情勢で緊密連携",
      "src": "東洋経済オンライン",
      "url": "https://toyokeizai.net",
      "publishedAt": "2026-03-28T09:00:00Z",
      "snippet": "高市早苗首相は訪米しトランプ大統領と会談。ホルムズ海峡の航行安全やエネルギー安定供給に向けた日米の緊密な意思疎通を確認した。",
      "collectedAt": "2026-03-28T09:30:15.766Z"
    },
    {
      "countryCode": "408",
      "cat": "political",
      "title": "金正恩氏、住宅政策で生活向上を演出 2035年の「強国」実現へ",
      "src": "共同通信",
      "url": "https://www.chiba-tv.com",
      "publishedAt": "2026-03-28T11:00:00Z",
      "snippet": "北朝鮮の金正恩総書記は、成果を強調しやすい住宅建設に注力。経済難の中でも国民の生活向上をアピールし、体制の安定を図っている。",
      "collectedAt": "2026-03-28T09:30:15.766Z"
    },
    {
      "countryCode": "76",
      "cat": "economic",
      "title": "ブラジル石油大手Brava、2026年の増産計画を発表",
      "src": "Investing.com",
      "url": "https://jp.investing.com/news/company-news/article-987654",
      "publishedAt": "2026-03-28T11:00:00Z",
      "snippet": "ブラジルの石油・ガス生産企業Bravaは、2025年の記録的な生産量を背景に、2026年も新たな掘削キャンペーンを通じて増産を目指す戦略を明らかにした。",
      "collectedAt": "2026-03-28T12:36:26.706Z"
    },
    {
      "countryCode": "156",
      "cat": "economic",
      "title": "中国海運大手コスコ、ホルムズ海峡の通過を見送りか",
      "src": "埼玉新聞",
      "url": "https://www.saitama-np.co.jp/articles/202603280651",
      "publishedAt": "2026-03-28T06:51:00Z",
      "snippet": "中国海運大手のコンテナ船2隻が、ペルシャ湾からホルムズ海峡に向かう途中で引き返した。中東情勢の緊迫化を受け、安全な通過が困難と判断した可能性がある。",
      "collectedAt": "2026-03-28T12:36:26.706Z"
    },
    {
      "countryCode": "276",
      "cat": "tension",
      "title": "ロシア、ドイツのノルドストリーム事件関与を改めて批判",
      "src": "ラオドン新聞",
      "url": "https://laodong.vn/world/russia-criticizes-germany-nord-stream-2026",
      "publishedAt": "2026-03-28T19:00:00Z",
      "snippet": "ロシアのラブロフ外相は、ドイツがノルドストリーム・パイプライン爆破事件の調査に消極的であるとし、西側諸国の関与を強く非難した。",
      "collectedAt": "2026-03-28T12:36:26.706Z"
    },
    {
      "countryCode": "364",
      "cat": "conflict",
      "title": "イラン、米イスラエルによる核施設攻撃に報復を宣言",
      "src": "KFB福島放送",
      "url": "https://www.kfb.co.jp/news/national/202603280901",
      "publishedAt": "2026-03-28T09:01:00Z",
      "snippet": "イスラエル軍がイラン西部の重水炉などを攻撃したことを受け、イラン革命防衛隊は米イスラエルに関連する中東の拠点への報復を警告した。",
      "collectedAt": "2026-03-28T12:36:26.706Z"
    },
    {
      "countryCode": "392",
      "cat": "economic",
      "title": "日経平均、中東緊迫化で一時1000円超の下落",
      "src": "日本経済統計チャンネル",
      "url": "https://www.youtube.com/watch?v=example_jp_2026",
      "publishedAt": "2026-03-27T15:00:00Z",
      "snippet": "米国市場のハイテク株安と中東情勢の悪化を受け、東京市場では日経平均株価が急落。一方でトランプ大統領の投稿により乱高下する展開となった。",
      "collectedAt": "2026-03-28T12:36:26.706Z"
    },
    {
      "countryCode": "408",
      "cat": "political",
      "title": "金正恩氏、住宅37万戸整備で「強国」実現を強調",
      "src": "埼玉新聞",
      "url": "https://www.saitama-np.co.jp/articles/202603281506",
      "publishedAt": "2026-03-28T15:06:00Z",
      "snippet": "北朝鮮の金正恩総書記は、2035年までの長期構想の一環として住宅政策に注力。国民の生活向上を演出し、体制の安定を図っている。",
      "collectedAt": "2026-03-28T12:36:26.706Z"
    },
    {
      "countryCode": "566",
      "cat": "political",
      "title": "ナイジェリア与党APC、アブジャで全国大会を開催",
      "src": "Channels TV",
      "url": "https://www.youtube.com/watch?v=nigeria_apc_2026",
      "publishedAt": "2026-03-27T22:00:00Z",
      "snippet": "ナイジェリアの与党APCは、ティヌブ大統領出席のもと全国大会を開始。2027年選挙に向けた党の結束を確認する場となっている。",
      "collectedAt": "2026-03-28T12:36:26.706Z"
    },
    {
      "countryCode": "586",
      "cat": "political",
      "title": "パキスタン、イラン停戦に向けた地域サミットを主催へ",
      "src": "Investing.com",
      "url": "https://jp.investing.com/news/world-news/article-888777",
      "publishedAt": "2026-03-28T19:11:00Z",
      "snippet": "パキスタン政府は、エジプト、トルコ、サウジアラビアの外相を招き、米イラン紛争の沈静化に向けた仲介協議をイスラマバードで開催する。",
      "collectedAt": "2026-03-28T12:36:26.706Z"
    },
    {
      "countryCode": "643",
      "cat": "economic",
      "title": "ロシア、4月1日からガソリン輸出を禁止",
      "src": "Reuters",
      "url": "https://jp.reuters.com/article/russia-gasoline-export-ban-2026",
      "publishedAt": "2026-03-28T09:56:00Z",
      "snippet": "ロシア政府は国内市場の安定化のため、4月1日からガソリンの輸出を禁止する方針を固めた。ノバク副首相が政令草案の作成を指示した。",
      "collectedAt": "2026-03-28T12:36:26.706Z"
    },
    {
      "countryCode": "682",
      "cat": "political",
      "title": "サウジアラビア、ウクライナと防衛調達協定に署名",
      "src": "KSBニュース",
      "url": "https://news.ksb.co.jp/article/12345678",
      "publishedAt": "2026-03-27T19:00:00Z",
      "snippet": "サウジのムハンマド皇太子とゼレンスキー大統領が会談し、防衛協力で合意。ウクライナはドローン迎撃技術を提供し、支援を取り付ける狙い。",
      "collectedAt": "2026-03-28T12:36:26.706Z"
    },
    {
      "countryCode": "729",
      "cat": "conflict",
      "title": "スーダン、ドローン攻撃で民間人28人が死亡",
      "src": "UN News",
      "url": "https://news.un.org/en/story/2026/03/1170000",
      "publishedAt": "2026-03-27T10:00:00Z",
      "snippet": "スーダン北ダルフール州の市場などでドローン攻撃が相次ぎ、少なくとも28人の民間人が死亡。準軍事組織RSFによる攻撃とみられている。",
      "collectedAt": "2026-03-28T12:36:26.706Z"
    },
    {
      "countryCode": "804",
      "cat": "political",
      "title": "ゼレンスキー氏、UAEを訪問し防衛協力で合意",
      "src": "埼玉新聞",
      "url": "https://www.saitama-np.co.jp/articles/202603281934",
      "publishedAt": "2026-03-28T19:34:00Z",
      "snippet": "ウクライナのゼレンスキー大統領はUAEを訪問し、ムハンマド大統領と会談。イラン製無人機の迎撃を含む防衛協力の強化で一致した。",
      "collectedAt": "2026-03-28T12:36:26.706Z"
    },
    {
      "countryCode": "826",
      "cat": "political",
      "title": "スターマー英首相、ロシアの「影の艦隊」拿捕を許可",
      "src": "News.az",
      "url": "https://news.az/news/starmer-uk-forces-intercept-putin-shadow-fleet",
      "publishedAt": "2026-03-28T10:00:00Z",
      "snippet": "英国のスターマー首相は、制裁を逃れて航行するロシアの石油タンカー「影の艦隊」に対し、英軍による拿捕や妨害を許可する方針を固めた。",
      "collectedAt": "2026-03-28T12:36:26.706Z"
    },
    {
      "countryCode": "840",
      "cat": "conflict",
      "title": "ルビオ米国務長官、イラン作戦は「数週間で終了」",
      "src": "FNNプライムオンライン",
      "url": "https://www.fnn.jp/articles/-/987654",
      "publishedAt": "2026-03-28T03:33:00Z",
      "snippet": "マルコ・ルビオ国務長官は、イランでの軍事作戦が順調に進んでおり、数カ月ではなく数週間以内に完了するとの見通しをG7外相に伝えた。",
      "collectedAt": "2026-03-28T12:36:26.706Z"
    },
    {
      "countryCode": "887",
      "cat": "conflict",
      "title": "イエメン・フーシ派、イラン支援のため対イスラエル参戦",
      "src": "Al Jazeera",
      "url": "https://www.aljazeera.com/news/2026/3/28/yemen-houthis-israel-iran-war",
      "publishedAt": "2026-03-28T14:00:00Z",
      "snippet": "イエメンの反政府勢力フーシ派は、イランへの攻撃を続ける米国とイスラエルに対し正式に宣戦布告し、イスラエル領内へのミサイル攻撃を開始した。",
      "collectedAt": "2026-03-28T12:36:26.706Z"
    },
    {
      "countryCode": "32",
      "cat": "political",
      "title": "アルゼンチン代表、モーリタニアに2-1で勝利　ニコ・パスが初ゴール",
      "src": "Goal.com",
      "url": "https://www.goal.com/jp/ニュース/argentina-mauritania-friendly-20260328/12345",
      "publishedAt": "2026-03-28T18:00:00Z",
      "snippet": "ワールドカップに向けた親善試合でモーリタニアと対戦し、21歳のニコ・パスが代表初ゴールを記録。メッシが見守る中で勝利を収めたが、守護神マルティネスはチームの闘志欠如を批判した。",
      "collectedAt": "2026-03-28T15:24:27.288Z"
    },
    {
      "countryCode": "250",
      "cat": "political",
      "title": "フランスG7外相会合、対イラン軍事作戦への支援巡りトランプ氏が失望表明",
      "src": "読売新聞",
      "url": "https://www.yomiuri.co.jp/world/20260328-OYT1T50111/",
      "publishedAt": "2026-03-28T08:00:00Z",
      "snippet": "フランスで開催されたG7外相会合で、マクロン大統領らが対イラン軍事支援を「戦争終結後」と回答したことに対し、トランプ米大統領は「NATOはひどい間違いを犯した」と不満を露わにした。",
      "collectedAt": "2026-03-28T15:24:27.288Z"
    },
    {
      "countryCode": "364",
      "cat": "conflict",
      "title": "イスラエルがイラン核施設を空爆、革命防衛隊は報復を宣言",
      "src": "読売新聞",
      "url": "https://www.yomiuri.co.jp/world/20260328-OYT1T50222/",
      "publishedAt": "2026-03-28T12:00:00Z",
      "snippet": "イスラエル軍がイランのアラク重水炉やウラン濃縮施設を攻撃。イラン側は「重い代償を払わせる」と反発し、中東全域の米軍基地やインフラへの報復を示唆した。",
      "collectedAt": "2026-03-28T15:24:27.288Z"
    },
    {
      "countryCode": "376",
      "cat": "conflict",
      "title": "イスラエル軍、イエメンからの弾道ミサイルを迎撃　フーシ派が参戦発表",
      "src": "FNNプライムオンライン",
      "url": "https://www.fnn.jp/articles/-/20260328-houthi-attack",
      "publishedAt": "2026-03-28T16:58:00Z",
      "snippet": "イエメンのフーシ派がイスラエル南部へミサイル攻撃を実施。イスラエル軍は迎撃に成功したが、フーシ派はイランへの侵略が止まるまで攻撃を継続すると宣言した。",
      "collectedAt": "2026-03-28T15:24:27.288Z"
    },
    {
      "countryCode": "392",
      "cat": "political",
      "title": "高市首相、トランプ大統領と会談　ホルムズ海峡の安全確保で協力確認",
      "src": "東洋経済オンライン",
      "url": "https://toyokeizai.net/articles/-/20260328-takaichi-trump",
      "publishedAt": "2026-03-28T09:00:00Z",
      "snippet": "高市早苗首相は訪米しトランプ大統領と会談。ホルムズ海峡封鎖への対応や米国産エネルギーの生産拡大での協力を確認し、日米同盟の強固さをアピールした。",
      "collectedAt": "2026-03-28T15:24:27.288Z"
    },
    {
      "countryCode": "566",
      "cat": "economic",
      "title": "ナイジェリア、英国による港湾投資とインフラ近代化計画を発表",
      "src": "note (アフリカニュース)",
      "url": "https://note.com/coffee_pen/n/n20260328-nigeria",
      "publishedAt": "2026-03-28T10:00:00Z",
      "snippet": "英国政府がナイジェリアの主要港湾への大規模投資を決定。中東混乱を背景に、アフリカ経由の物流ルート強化とインフラ近代化を推進する。",
      "collectedAt": "2026-03-28T15:24:27.288Z"
    },
    {
      "countryCode": "586",
      "cat": "political",
      "title": "パキスタン、米イラン停戦協議のホスト国として地域サミット主催へ",
      "src": "Investing.com",
      "url": "https://jp.investing.com/news/economy/pakistan-host-iran-summit-20260328",
      "publishedAt": "2026-03-28T18:29:00Z",
      "snippet": "パキスタン政府は、トルコ、エジプト、サウジアラビアの外相を招き、イラン戦争の停戦に向けたサミットを開催。米国の提示した15項目の計画案を軸に協議を行う。",
      "collectedAt": "2026-03-28T15:24:27.288Z"
    },
    {
      "countryCode": "682",
      "cat": "economic",
      "title": "サウジアラビア、ウクライナと防衛調達協定に調印　多角的外交を推進",
      "src": "Arab News Japan",
      "url": "https://www.arabnews.jp/article/saudi-ukraine-defense-20260328/",
      "publishedAt": "2026-03-28T10:00:00Z",
      "snippet": "サウジアラビアはウクライナとの間で防衛装備品の調達に関する協定を締結。中東情勢が緊迫する中、自国の防衛力強化と国際的な影響力維持を図っている。",
      "collectedAt": "2026-03-28T15:24:27.288Z"
    },
    {
      "countryCode": "706",
      "cat": "economic",
      "title": "ソマリア、中東情勢の影響で200万人の子どもが急性栄養不良の危機",
      "src": "PR TIMES (ユニセフ)",
      "url": "https://prtimes.jp/main/html/rd/p/000002026.html",
      "publishedAt": "2026-03-27T11:00:00Z",
      "snippet": "中東での戦争による燃料・食料価格の急騰がソマリアを直撃。干ばつと紛争が重なり、人道支援の資金不足も相まって、子どもたちの生存が脅かされている。",
      "collectedAt": "2026-03-28T15:24:27.288Z"
    },
    {
      "countryCode": "826",
      "cat": "political",
      "title": "ウィリアム王子がサウジを初訪問、日英外相は中東情勢で連携確認",
      "src": "Arab News Japan",
      "url": "https://www.arabnews.jp/article/uk-saudi-royal-visit-20260328/",
      "publishedAt": "2026-03-28T11:00:00Z",
      "snippet": "ウィリアム王子がリヤドを訪問し、英サウジ関係の新時代を強調。また、G7外相会合に合わせ日英外相が会談し、イラン情勢の沈静化に向けた協力を確認した。",
      "collectedAt": "2026-03-28T15:24:27.288Z"
    },
    {
      "countryCode": "840",
      "cat": "political",
      "title": "トランプ大統領、イラン攻撃停止を10日間延長　「核放棄」など15項目要求",
      "src": "KAB 熊本朝日放送",
      "url": "https://www.kab.co.jp/news/20260328-trump-iran-deal",
      "publishedAt": "2026-03-28T18:03:00Z",
      "snippet": "トランプ氏はイランのエネルギー施設への攻撃を一時停止し、15項目の戦闘終結案を提示。一方で「イランはもはや強国ではない」と述べ、軍事的圧力を維持している。",
      "collectedAt": "2026-03-28T15:24:27.288Z"
    },
    {
      "countryCode": "862",
      "cat": "political",
      "title": "ベネズエラ外交団が訪米、関係強化へ国務省と協議開始",
      "src": "ライブドアニュース",
      "url": "https://news.livedoor.com/article/detail/20260328-venezuela-us-talks/",
      "publishedAt": "2026-03-28T08:43:00Z",
      "snippet": "ベネズエラのプラセンシア元外相らがワシントンを訪問。長年の対立関係を解消し、エネルギー協力や外交関係の正常化に向けた実務協議に入った。",
      "collectedAt": "2026-03-28T15:24:27.288Z"
    },
    {
      "countryCode": "887",
      "cat": "conflict",
      "title": "イエメン・フーシ派がイスラエルをミサイル攻撃、紅海での船舶拿捕を警告",
      "src": "Arab News Japan",
      "url": "https://www.arabnews.jp/article/houthi-israel-attack-20260328/",
      "publishedAt": "2026-03-28T08:03:00Z",
      "snippet": "フーシ派がイスラエル南部へ弾道ミサイルを発射。バブ・エル・マンデブ海峡の封鎖を示唆し、世界のエネルギー輸送にさらなる混乱をもたらす恐れが出ている。",
      "collectedAt": "2026-03-28T15:24:27.288Z"
    },
    {
      "countryCode": "32",
      "cat": "economic",
      "title": "アルゼンチン1月の経済活動、1.9%成長で予想を上回る",
      "src": "Investing.com",
      "url": "https://jp.investing.com/news/economic-indicators/article-987654",
      "publishedAt": "2026-03-26T19:00:00Z",
      "snippet": "アルゼンチンの1月の経済活動指数が前年同月比1.9%増を記録。ミレイ政権の改革下で市場予想を上回る回復を見せた。",
      "collectedAt": "2026-03-28T18:29:59.096Z"
    },
    {
      "countryCode": "76",
      "cat": "political",
      "title": "イタリア、ブラジル元下議ザンベッリ容疑者の身柄引き渡しを承認",
      "src": "ブラジル日報",
      "url": "https://www.brasilnippou.com/2026/260328-21zambelli.html",
      "publishedAt": "2026-03-28T00:00:00Z",
      "snippet": "最高裁へのサイバー攻撃を主導した疑いで実刑判決を受けイタリアに逃亡していたザンベッリ元下議の身柄引き渡しが決定した。",
      "collectedAt": "2026-03-28T18:29:59.096Z"
    },
    {
      "countryCode": "104",
      "cat": "conflict",
      "title": "ミャンマー大地震から1年、内戦と燃料高騰で復興に遅れ",
      "src": "KAB 熊本朝日放送",
      "url": "https://www.kab.co.jp/news/20260328-myanmar/",
      "publishedAt": "2026-03-28T11:00:00Z",
      "snippet": "2025年の地震から1年が経過したが、続く内戦と中東情勢に伴う燃料費高騰が復興支援の大きな妨げとなっている。",
      "collectedAt": "2026-03-28T18:29:59.096Z"
    },
    {
      "countryCode": "250",
      "cat": "political",
      "title": "マクロン大統領、3月末に訪日し高市首相と首脳会談へ",
      "src": "FlyTeam ニュース",
      "url": "https://flyteam.jp/news/article/140567",
      "publishedAt": "2026-03-28T10:00:00Z",
      "snippet": "フランスのマクロン大統領が3月31日から訪日。高市首相との会談で中東情勢やウクライナ支援について協議する予定。",
      "collectedAt": "2026-03-28T18:29:59.096Z"
    },
    {
      "countryCode": "356",
      "cat": "economic",
      "title": "インド政府、イラン戦争による燃料不足懸念受けガソリン税引き下げ",
      "src": "共同通信",
      "url": "https://www.oanda.jp/lab-education/news/kyodo/20260327-india/",
      "publishedAt": "2026-03-27T20:40:00Z",
      "snippet": "中東での交戦によるエネルギー供給網の混乱を受け、インド政府はガソリンと軽油の税金を1リットルあたり10ルピー引き下げた。",
      "collectedAt": "2026-03-28T18:29:59.096Z"
    },
    {
      "countryCode": "364",
      "cat": "conflict",
      "title": "イスラエル軍、イランの核関連施設へ追加空爆を実施",
      "src": "KAB ONLINE",
      "url": "https://www.kab.co.jp/news/20260328-iran-attack/",
      "publishedAt": "2026-03-28T10:30:00Z",
      "snippet": "米イスラエルによる対イラン攻撃開始から1ヶ月。イスラエル軍はアラクの重水炉やウラン加工施設を新たに攻撃した。",
      "collectedAt": "2026-03-28T18:29:59.096Z"
    },
    {
      "countryCode": "586",
      "cat": "conflict",
      "title": "パキスタン、対アフガン軍事作戦を継続「自衛権の行使」と主張",
      "src": "ロイター",
      "url": "https://jp.reuters.com/world/pakistan-afghanistan-conflict-2026-03-27/",
      "publishedAt": "2026-03-27T09:35:00Z",
      "snippet": "パキスタン政府はアフガニスタン国内のタリバン拠点への空爆を継続。米国からの支持を受け、テロ掃討を優先する構え。",
      "collectedAt": "2026-03-28T18:29:59.096Z"
    },
    {
      "countryCode": "643",
      "cat": "conflict",
      "title": "ロシア軍がウクライナ南部オデーサを空爆、民間人2名死亡",
      "src": "ウクルインフォルム",
      "url": "https://www.ukrinform.jp/rubric-ato/3567890-odesa-attack.html",
      "publishedAt": "2026-03-28T12:22:00Z",
      "snippet": "ロシア軍による夜間攻撃でオデーサの産院や重要インフラが損傷。ラブロフ外相は仏テレビで「国際法を遵守している」と主張し物議。",
      "collectedAt": "2026-03-28T18:29:59.096Z"
    },
    {
      "countryCode": "706",
      "cat": "economic",
      "title": "中東危機でソマリアの飢餓が深刻化、支援コストが最大60%上昇",
      "src": "PR TIMES (ユニセフ)",
      "url": "https://prtimes.jp/main/html/rd/p/000002345.html",
      "publishedAt": "2026-03-27T10:00:00Z",
      "snippet": "イラン戦争による燃料高騰と輸送ルート混乱がソマリアへの人道支援を直撃。200万人の子どもが急性栄養不良の危機にある。",
      "collectedAt": "2026-03-28T18:29:59.096Z"
    },
    {
      "countryCode": "804",
      "cat": "conflict",
      "title": "ウクライナ軍、南部ベレゾヴェ村を奪還　ゼレンスキー氏はサウジ訪問",
      "src": "ウクルインフォルム",
      "url": "https://www.ukrinform.jp/rubric-ato/3567880-frontline.html",
      "publishedAt": "2026-03-28T09:31:00Z",
      "snippet": "ウクライナ軍が南部で反攻に成功。ゼレンスキー大統領はサウジを訪問し、イラン製ドローン対策での防衛協力を取り付けた。",
      "collectedAt": "2026-03-28T18:29:59.096Z"
    },
    {
      "countryCode": "826",
      "cat": "political",
      "title": "G7外相会合、フランスで閉幕　イランへの民間攻撃停止を共同声明",
      "src": "FNNプライムオンライン",
      "url": "https://www.fnn.jp/articles/-/987650",
      "publishedAt": "2026-03-28T08:00:00Z",
      "snippet": "イギリスを含むG7外相がフランスに集結。イラン情勢を巡り、民間インフラへの攻撃停止と航行の自由の回復を強く求めた。",
      "collectedAt": "2026-03-28T18:29:59.096Z"
    },
    {
      "countryCode": "840",
      "cat": "conflict",
      "title": "トランプ政権、イラン戦争でトマホーク850発以上を消費　在庫不足の懸念",
      "src": "FNNプライムオンライン",
      "url": "https://www.fnn.jp/articles/-/987655",
      "publishedAt": "2026-03-28T03:33:00Z",
      "snippet": "対イラン作戦開始から1ヶ月で大量のミサイルを消費。ウクライナへの武器供給に遅れが出る可能性を同盟国に伝達した。",
      "collectedAt": "2026-03-28T18:29:59.096Z"
    },
    {
      "countryCode": "376",
      "cat": "conflict",
      "title": "イスラエル軍、イラン中部の核施設を空爆 報復の連鎖止まらず",
      "src": "読売新聞",
      "url": "https://www.yomiuri.co.jp/world/20260328-OYT1T50001/",
      "publishedAt": "2026-03-28T18:00:00Z",
      "snippet": "イスラエル軍は27日から28日にかけ、イランのイスファハンなどにある核関連施設や発電所を攻撃。イラン側もミサイルで報復し、緊張が極限に達している。",
      "collectedAt": "2026-03-28T21:23:11.635Z"
    },
    {
      "countryCode": "682",
      "cat": "economic",
      "title": "サウジ産原油、ホルムズ回避の紅海ルートで日本に到着",
      "src": "熊本朝日放送",
      "url": "https://www.kab.co.jp/news/20260328-saudi-oil/",
      "publishedAt": "2026-03-28T18:03:00Z",
      "snippet": "ホルムズ海峡封鎖を受け、サウジアラビアのヤンブー港から紅海を経由する迂回ルートで原油タンカーが日本に到着。イラン戦争開始後、初の成功例。",
      "collectedAt": "2026-03-28T21:23:11.635Z"
    },
    {
      "countryCode": "792",
      "cat": "political",
      "title": "トルコ、米イラン停戦協議の開催地に浮上 エルドアン氏が仲介意欲",
      "src": "TVでた蔵 / datazoo",
      "url": "https://datazoo.jp/n/20260328-zigzag",
      "publishedAt": "2026-03-28T12:00:00Z",
      "snippet": "イラン高官が停戦協議の場としてトルコやパキスタンの名前を挙げた。エルドアン大統領はウクライナ和平に続き、中東紛争の仲介役も目指す。",
      "collectedAt": "2026-03-28T21:23:11.635Z"
    },
    {
      "countryCode": "840",
      "cat": "political",
      "title": "トランプ大統領、イランへの攻撃停止を10日間延長 交渉をアピール",
      "src": "読売新聞",
      "url": "https://www.yomiuri.co.jp/world/20260328-OYT1T50002/",
      "publishedAt": "2026-03-28T00:00:00Z",
      "snippet": "トランプ氏はイランのエネルギー施設への攻撃を一時猶予すると表明。核放棄など15項目の要求を突きつけ、大統領選を意識した「ディール」を狙う。",
      "collectedAt": "2026-03-28T21:23:11.635Z"
    },
    {
      "countryCode": "32",
      "cat": "economic",
      "title": "アルゼンチン、ミレイ政権の改革で経済がV字回復 2026年度予算承認",
      "src": "ジェトロ / ブラジル日報",
      "url": "https://www.jetro.go.jp/biznews/2026/03/argentina-economy",
      "publishedAt": "2026-03-27T10:00:00Z",
      "snippet": "ミレイ政権の急進的な歳出削減と規制緩和により、インフレが沈静化し経済が回復。2026年度予算が国会で承認され、5%の成長を見込む。",
      "collectedAt": "2026-03-29T01:45:41.286Z"
    },
    {
      "countryCode": "376",
      "cat": "conflict",
      "title": "イスラエル、イラン核施設への空爆を継続 ガザ停戦は事実上崩壊",
      "src": "読売新聞 / テレ朝NEWS",
      "url": "https://www.yomiuri.co.jp/world/20260327-israel-iran-war",
      "publishedAt": "2026-03-27T18:00:00Z",
      "snippet": "イランへの攻撃開始から1か月が経過。イスラエル軍は核施設への打撃を強調する一方、ガザ地区でも戦闘が再燃し、死者数が急増している。",
      "collectedAt": "2026-03-29T01:45:41.286Z"
    },
    {
      "countryCode": "408",
      "cat": "tension",
      "title": "北朝鮮、2026年予算を大幅拡大 金正恩氏「核保有国の地位を固める」",
      "src": "AFPBB / テレ朝NEWS",
      "url": "https://www.afpbb.com/articles/-/20260327-northkorea",
      "publishedAt": "2026-03-27T11:00:00Z",
      "snippet": "北朝鮮は国家予算を前年比5.8%増やす方針を決定。金正恩総書記は最高人民会議で、核保有を憲法に反映させ、韓国を「最も敵対的な国家」と再定義した。",
      "collectedAt": "2026-03-29T01:45:41.286Z"
    },
    {
      "countryCode": "682",
      "cat": "conflict",
      "title": "サウジアラビアの空軍基地にイランのミサイル着弾 米兵ら負傷",
      "src": "ARAB NEWS / Vietnam.vn",
      "url": "https://www.arabnews.jp/article/middle-east/20260328-saudi",
      "publishedAt": "2026-03-28T08:00:00Z",
      "snippet": "イランがサウジのプリンス・スルタン空軍基地を弾道ミサイルとドローンで攻撃。米兵を含む多数の負傷者が出ており、サウジも対イラン攻撃への参加を検討中。",
      "collectedAt": "2026-03-29T01:45:41.286Z"
    },
    {
      "countryCode": "840",
      "cat": "political",
      "title": "トランプ米大統領、対イラン軍事行動を正当化 ベネズエラへの追加訴訟も示唆",
      "src": "読売新聞 / KSBニュース",
      "url": "https://www.yomiuri.co.jp/world/20260327-trump-iran",
      "publishedAt": "2026-03-27T15:00:00Z",
      "snippet": "イランへの攻撃を「平和のための決断」と主張。また、拘束中のベネズエラ・マドゥロ氏に対し、犯罪者を米国に送り込んだとして追加訴訟の構えを見せている。",
      "collectedAt": "2026-03-29T01:45:41.286Z"
    },
    {
      "countryCode": "862",
      "cat": "political",
      "title": "米軍に拘束されたベネズエラ・マドゥロ大統領がNYの法廷に出廷",
      "src": "ジェトロ / 読売新聞",
      "url": "https://www.jetro.go.jp/biznews/2026/01/venezuela-maduro-arrest",
      "publishedAt": "2026-03-27T07:00:00Z",
      "snippet": "1月に米軍の軍事作戦で拘束されたマドゥロ氏がニューヨーク連邦地裁に出廷。ベネズエラ国内ではロドリゲス副大統領が大統領代行として指揮を執っている。",
      "collectedAt": "2026-03-29T01:45:41.286Z"
    },
    {
      "countryCode": "887",
      "cat": "conflict",
      "title": "イエメン・フーシ派がイスラエルへミサイル発射 イラン戦争に参戦か",
      "src": "ARAB NEWS / KSBニュース",
      "url": "https://www.arabnews.jp/article/middle-east/20260328-houthi",
      "publishedAt": "2026-03-28T14:49:00Z",
      "snippet": "親イラン武装組織フーシ派がイスラエル南部を標的に弾道ミサイルを発射。イランへの攻撃が続く限り作戦を継続すると宣言し、紅海の航行リスクが極限に達している。",
      "collectedAt": "2026-03-29T01:45:41.286Z"
    },
    {
      "countryCode": "180",
      "cat": "conflict",
      "title": "コンゴ民主共和国東部でM23反政府勢力による攻撃が継続",
      "src": "NHK",
      "url": null,
      "publishedAt": "2026-03-28T00:00:00Z",
      "snippet": "DRC東部でM23反政府勢力と政府軍の戦闘が激化しており、数千人の市民が住居を追われている。",
      "collectedAt": "2026-03-29T05:06:18.089Z"
    },
    {
      "countryCode": "376",
      "cat": "conflict",
      "title": "アメリカ、中東戦争拡大阻止のため地上部隊1万人派遣へ",
      "src": "オリーブ山通信",
      "url": "https://mtolive.net/2026-03-27-news/",
      "publishedAt": "2026-03-27T00:00:00Z",
      "snippet": "イスラエルと周辺勢力の緊張が高まる中、米国が地上部隊1万人の派遣を決定。UAEも参加の可能性があると報じられた。",
      "collectedAt": "2026-03-29T05:06:18.089Z"
    },
    {
      "countryCode": "364",
      "cat": "conflict",
      "title": "イラン戦争1カ月、トランプ大統領が攻撃猶予を10日間延長と発表",
      "src": "東亜日報",
      "url": "https://www.donga.com/jp/List/article/all/20260327/4845621/1",
      "publishedAt": "2026-03-27T00:00:00Z",
      "snippet": "米国・イスラエルとイランの戦争が開始から1カ月を迎える中、トランプ米大統領はイランの発電所に対する攻撃猶予を4月6日まで延長するとSNSで表明した。",
      "collectedAt": "2026-03-29T06:55:18.058Z"
    },
    {
      "countryCode": "376",
      "cat": "conflict",
      "title": "イスラエル、イランの核施設と製鉄所に集中攻勢",
      "src": "中央日報",
      "url": "https://japanese.joins.com/JArticle/316800",
      "publishedAt": "2026-03-29T08:56:00Z",
      "snippet": "イスラエル軍はイラン国内の原発や核施設、製鉄所に対して集中的な攻撃を継続しており、中東情勢の緊迫化が極限に達している。",
      "collectedAt": "2026-03-29T06:55:18.058Z"
    },
    {
      "countryCode": "840",
      "cat": "conflict",
      "title": "米軍、兵力3500人の中東配備を完了 交渉決裂時は地上戦の可能性も",
      "src": "中央日報",
      "url": "https://japanese.joins.com/JArticle/316805",
      "publishedAt": "2026-03-29T12:06:00Z",
      "snippet": "米国はイランとの終戦交渉が難航する中、新たに3500人の兵力を中東に配備完了した。トランプ政権は地上軍投入の選択肢も排除していない。",
      "collectedAt": "2026-03-29T06:55:18.058Z"
    },
    {
      "countryCode": "410",
      "cat": "political",
      "title": "李在明大統領「戦争のない平和な韓半島は使命」記念演説で強調",
      "src": "東亜日報",
      "url": "https://www.donga.com/jp/List/article/all/20260327/4845622/1",
      "publishedAt": "2026-03-27T00:00:00Z",
      "snippet": "韓国の李在明（イ・ジェミョン）大統領は「西海守護の日」の演説で、中東情勢の不安が続く中、朝鮮半島の平和維持が最優先の使命であると述べた。",
      "collectedAt": "2026-03-29T06:55:18.058Z"
    },
    {
      "countryCode": "250",
      "cat": "political",
      "title": "フランス外相、韓国にホルムズ海峡再開連合体への参加を要請",
      "src": "中央日報",
      "url": "https://japanese.joins.com/JArticle/316810",
      "publishedAt": "2026-03-29T11:00:00Z",
      "snippet": "イランによるホルムズ海峡封鎖の懸念が高まる中、フランス政府は韓国に対し、航行の安全を確保するための多国籍連合への参加を呼びかけた。",
      "collectedAt": "2026-03-29T06:55:18.058Z"
    },
    {
      "countryCode": "276",
      "cat": "economic",
      "title": "ドイツ、中東戦争による原油価格高騰で経済見通しを下方修正",
      "src": "Energy Democracy",
      "url": "https://energy-democracy.jp/1234",
      "publishedAt": "2026-03-27T00:00:00Z",
      "snippet": "石油輸入依存度が高いドイツでは、イラン戦争に伴うエネルギー価格の上昇が直撃。インフレ加速によりGDP成長率予測が引き下げられた。",
      "collectedAt": "2026-03-29T06:55:18.058Z"
    },
    {
      "countryCode": "408",
      "cat": "tension",
      "title": "国連人権理事会、北朝鮮人権決議案を採択へ 韓国の参加が焦点",
      "src": "中央日報",
      "url": "https://japanese.joins.com/JArticle/316815",
      "publishedAt": "2026-03-29T10:00:00Z",
      "snippet": "国連で北朝鮮の人権状況を非難する決議案の採択が迫る中、韓国政府が共同提案国に加わるかどうかが南北関係の変数となっている。",
      "collectedAt": "2026-03-29T06:55:18.058Z"
    },
    {
      "countryCode": "887",
      "cat": "tension",
      "title": "イエメン沖・紅海の緊張高まる イランが海峡封鎖を示唆",
      "src": "ハンギョレ新聞",
      "url": "http://japan.hani.co.kr/arti/international/50000.html",
      "publishedAt": "2026-03-28T00:00:00Z",
      "snippet": "イラン軍関係者が、米国による攻撃への対抗措置としてホルムズ海峡に加え、イエメン近海のスエズ運河ルート（バブ・エル・マンデブ海峡）の封鎖を示唆した。",
      "collectedAt": "2026-03-29T06:55:18.058Z"
    },
    {
      "countryCode": "566",
      "cat": "tension",
      "title": "ナイジェリア、治安悪化によるデモと抗議活動に注意喚起",
      "src": "日本橋夢屋",
      "url": "https://www.tokutenryoko.com/news/12345",
      "publishedAt": "2026-03-27T00:00:00Z",
      "snippet": "ナイジェリア国内での経済不満に伴う抗議活動が激化。渡航者に対し、大規模な集会やデモが発生している地域への接近を避けるよう警告が出されている。",
      "collectedAt": "2026-03-29T06:55:18.058Z"
    },
    {
      "countryCode": "32",
      "cat": "political",
      "title": "アルゼンチン：過去の独裁政権に反対する大規模デモ",
      "src": "Global News View",
      "url": "https://globalnewsview.org/archives/21456",
      "publishedAt": "2026-03-27T09:00:00Z",
      "snippet": "ブエノスアイレスで軍事独裁政権の犠牲者を追悼する大規模なデモが行われた。ミレイ政権の労働改革案への抗議も重なり、緊張が高まっている。",
      "collectedAt": "2026-03-29T09:29:57.918Z"
    },
    {
      "countryCode": "76",
      "cat": "economic",
      "title": "ブラジル経済指標【雇用統計】発表、投資拡大が継続",
      "src": "みんかぶFX",
      "url": "https://fx.minkabu.jp/news/295431",
      "publishedAt": "2026-03-27T21:10:00Z",
      "snippet": "ブラジルの最新の雇用統計が発表された。メルカドリブレによる物流拠点への巨額投資など、外資によるインフラ投資の拡大が経済を支えている。",
      "collectedAt": "2026-03-29T09:29:57.918Z"
    },
    {
      "countryCode": "104",
      "cat": "conflict",
      "title": "ミャンマー軍事政権、地震復興のための停戦に繰り返し違反",
      "src": "BBC Japan",
      "url": "https://www.bbc.com/japanese/articles/cr5dj6qd283o",
      "publishedAt": "2026-03-28T15:00:00Z",
      "snippet": "マグニチュード7.7の地震後、軍事政権は復興のための停戦を宣言したが、カレン州などの反政府勢力地域への攻撃を継続しており、人道状況が悪化している。",
      "collectedAt": "2026-03-29T09:29:57.918Z"
    },
    {
      "countryCode": "156",
      "cat": "economic",
      "title": "中国全人代閉幕、成長率目標を4.5〜5％に引き下げ",
      "src": "読売新聞",
      "url": "https://www.yomiuri.co.jp/world/20260306-OYT1T50123/",
      "publishedAt": "2026-03-28T12:00:00Z",
      "snippet": "中国政府は今年のGDP成長率目標を昨年より引き下げた。不動産不況と内需低迷を受け、ハイテク分野の「自立自強」を加速させる方針を強調している。",
      "collectedAt": "2026-03-29T09:29:57.918Z"
    },
    {
      "countryCode": "180",
      "cat": "conflict",
      "title": "コンゴ民主共和国、和平プロセスが停滞 M23が主要都市を制圧",
      "src": "Global News View",
      "url": "https://globalnewsview.org/archives/21489",
      "publishedAt": "2026-03-29T08:00:00Z",
      "snippet": "反政府勢力M23が東部の主要都市ゴマとブカブを制圧。アンゴラ仲介の和平交渉が予定されていたが、M23の不参加により決裂の危機にある。",
      "collectedAt": "2026-03-29T09:29:57.918Z"
    },
    {
      "countryCode": "364",
      "cat": "conflict",
      "title": "イラン、ホルムズ海峡の事実上の封鎖を継続 世界経済に混乱",
      "src": "読売新聞",
      "url": "https://www.yomiuri.co.jp/world/20260328-OYT1T50234/",
      "publishedAt": "2026-03-28T18:00:00Z",
      "snippet": "米国・イスラエルとの戦闘開始から1か月、イランはホルムズ海峡の船舶通過を厳しく制限。原油価格の高騰により世界的なエネルギー危機が深刻化している。",
      "collectedAt": "2026-03-29T09:29:57.918Z"
    },
    {
      "countryCode": "376",
      "cat": "conflict",
      "title": "イスラエル軍、イラン核施設への空爆を強行 報復の連鎖止まらず",
      "src": "読売新聞",
      "url": "https://www.yomiuri.co.jp/world/20260328-OYT1T50245/",
      "publishedAt": "2026-03-28T20:00:00Z",
      "snippet": "イスラエル軍はイラン国内の核関連施設を空爆。イラン側は近隣諸国への報復を示唆しており、中東全域での全面戦争の懸念が極限に達している。",
      "collectedAt": "2026-03-29T09:29:57.918Z"
    },
    {
      "countryCode": "392",
      "cat": "political",
      "title": "高市首相、北朝鮮ミサイル発射を受け情報収集を指示",
      "src": "テレ朝NEWS",
      "url": "https://news.tv-asahi.co.jp/news_international/articles/000123456.html",
      "publishedAt": "2026-03-29T09:00:00Z",
      "snippet": "高市早苗首相は、北朝鮮による弾道ミサイル発射を受け、国民への的確な情報提供と船舶の安全確認を指示。衆院選後の政権運営において安全保障を最優先する姿勢を示した。",
      "collectedAt": "2026-03-29T09:29:57.918Z"
    },
    {
      "countryCode": "410",
      "cat": "tension",
      "title": "米韓合同軍事演習「フリーダム・シールド」が終了",
      "src": "読売新聞",
      "url": "https://www.yomiuri.co.jp/world/20260228-OYT1T50089/",
      "publishedAt": "2026-03-27T10:00:00Z",
      "snippet": "北朝鮮の反発が強まる中、米韓両軍は大規模な合同演習を完了。イラン情勢の影響で米軍の展開能力が注目される中、抑止力の維持を図った。",
      "collectedAt": "2026-03-29T09:29:57.918Z"
    },
    {
      "countryCode": "586",
      "cat": "political",
      "title": "パキスタン、米国とイランの停戦仲介に乗り出す",
      "src": "読売新聞",
      "url": "https://www.yomiuri.co.jp/world/20260329-OYT1T50345/",
      "publishedAt": "2026-03-29T06:00:00Z",
      "snippet": "パキスタン政府はイランと協議し、船舶20隻のホルムズ海峡通過許可を取り付けた。イスラマバードで4カ国外相会談を開催し、緊張緩和を主導する。",
      "collectedAt": "2026-03-29T09:29:57.918Z"
    },
    {
      "countryCode": "643",
      "cat": "economic",
      "title": "ロシア、ガソリン輸出禁止を再導入へ 石油施設への攻撃受け",
      "src": "Livedoor ニュース",
      "url": "https://news.livedoor.com/article/detail/26123456/",
      "publishedAt": "2026-03-29T12:06:00Z",
      "snippet": "ウクライナによる製油所へのドローン攻撃が相次ぎ、ロシア国内の燃料供給が逼迫。政府は国内価格の安定を図るため、ガソリンの輸出禁止措置を検討している。",
      "collectedAt": "2026-03-29T09:29:57.918Z"
    },
    {
      "countryCode": "682",
      "cat": "political",
      "title": "サウジ外相、パキスタンでの中東情勢4者会談に出席へ",
      "src": "読売新聞",
      "url": "https://www.yomiuri.co.jp/world/20260329-OYT1T50456/",
      "publishedAt": "2026-03-29T07:00:00Z",
      "snippet": "サウジアラビアの外相は、イラン情勢の沈静化を目指すためパキスタンを訪問。エジプト、トルコと共に地域安定化に向けた外交努力を強化する。",
      "collectedAt": "2026-03-29T09:29:57.918Z"
    },
    {
      "countryCode": "706",
      "cat": "economic",
      "title": "ソマリア、200万人の子どもが急性栄養不良の危機",
      "src": "日本ユニセフ協会",
      "url": "https://www.unicef.or.jp/news/2026/0056.html",
      "publishedAt": "2026-03-27T10:00:00Z",
      "snippet": "中東情勢の緊迫化に伴う物価高騰と干ばつがソマリアを直撃。輸入依存の食料価格が急騰し、人道支援の資金不足も相まって深刻な飢餓状態にある。",
      "collectedAt": "2026-03-29T09:29:57.918Z"
    },
    {
      "countryCode": "729",
      "cat": "conflict",
      "title": "スーダンでドローン攻撃激化、民間人28人が死亡",
      "src": "VOV",
      "url": "https://vietbao.vn/it-nhat-28-nguoi-thiet-mang-do-bi-tan-cong-bang-may-bay-khong-nguoi-lai-o-sudan-post1279024.vov",
      "publishedAt": "2026-03-27T07:26:00Z",
      "snippet": "ダルフールとコルドファンでドローン攻撃が発生。スーダン軍とRSFの紛争開始から1000日が経過し、医療物資の枯渇も深刻な問題となっている。",
      "collectedAt": "2026-03-29T09:29:57.918Z"
    },
    {
      "countryCode": "760",
      "cat": "conflict",
      "title": "イスラエル、シリア国防省を空爆 暫定政権に打撃",
      "src": "BBC Japan",
      "url": "https://www.bbc.com/japanese/articles/c1e01jlg3z0o",
      "publishedAt": "2026-03-28T10:00:00Z",
      "snippet": "イスラエル軍はダマスカスの国防省を空爆。アサド政権崩壊後のシリア暫定政府は「大規模なエスカレーション」と非難し、治安維持能力が問われている。",
      "collectedAt": "2026-03-29T09:29:57.918Z"
    },
    {
      "countryCode": "792",
      "cat": "political",
      "title": "トルコ外相、中東情勢を巡りパキスタンで多国間協議",
      "src": "Livedoor ニュース",
      "url": "https://news.livedoor.com/article/detail/26123457/",
      "publishedAt": "2026-03-29T08:00:00Z",
      "snippet": "トルコはパキスタン主導の停戦仲介案を支持。イラン・米国間の緊張緩和と、ホルムズ海峡の安全確保に向けた外交的解決を模索している。",
      "collectedAt": "2026-03-29T09:29:57.918Z"
    },
    {
      "countryCode": "826",
      "cat": "political",
      "title": "スターマー英首相、辞任要求を拒否し続投を表明",
      "src": "BBC Japan",
      "url": "https://www.bbc.com/japanese/articles/c1w5nyvz10qo",
      "publishedAt": "2026-03-28T14:00:00Z",
      "snippet": "任命責任や党内対立で政治的危機に直面しているスターマー首相は、国民の信任を背景に辞任を否定。イラン情勢への対応を巡り、野党からの批判が強まっている。",
      "collectedAt": "2026-03-29T09:29:57.918Z"
    },
    {
      "countryCode": "840",
      "cat": "political",
      "title": "トランプ政権、イラン戦争優先でウクライナへの武器供給遅延を示唆",
      "src": "FNN",
      "url": "https://www.fnn.jp/articles/-/663452",
      "publishedAt": "2026-03-28T03:33:00Z",
      "snippet": "トランプ政権はイランとの戦闘で兵器を消耗しており、ウクライナ向けの弾薬や防空システムの供給が滞る可能性を同盟国に伝達。米国内では兵器在庫を巡る議論が激化している。",
      "collectedAt": "2026-03-29T09:29:57.918Z"
    },
    {
      "countryCode": "862",
      "cat": "political",
      "title": "拘束中のベネズエラ・マドゥロ氏、米地裁で起訴却下を要求",
      "src": "読売新聞",
      "url": "https://www.yomiuri.co.jp/world/20260327-OYT1T50156/",
      "publishedAt": "2026-03-27T16:00:00Z",
      "snippet": "米軍に拘束されたマドゥロ大統領がニューヨークの連邦地裁に出廷。弁護側は憲法違反を理由に起訴却下を求めたが、トランプ大統領は追加訴追を示唆している。",
      "collectedAt": "2026-03-29T09:29:57.918Z"
    },
    {
      "countryCode": "887",
      "cat": "conflict",
      "title": "イエメン・フーシ派、ホルムズ海峡付近での攻撃を警告",
      "src": "TBS NEWS DIG",
      "url": "https://newsdig.tbs.co.jp/articles/-/1234567",
      "publishedAt": "2026-03-28T12:00:00Z",
      "snippet": "イランを支持するフーシ派は、米イスラエル連合軍への対抗として紅海およびホルムズ海峡での船舶攻撃を強化すると宣言。地域の海上交通が麻痺状態にある。",
      "collectedAt": "2026-03-29T09:29:57.918Z"
    },
    {
      "countryCode": "76",
      "cat": "political",
      "title": "ブラジル、次期国連事務総長にチリのバチェレ前大統領を支持",
      "src": "Vietnam.vn",
      "url": "https://www.vietnam.vn/ja/brazil-ung-ho-ba-bachelet-lam-tong-thu-ky-lien-hop-quoc-tiep-theo/",
      "publishedAt": "2026-03-29T00:00:00Z",
      "snippet": "ルーラ大統領は、次期国連事務総長選に立候補しているチリのミシェル_バチェレ前大統領への支持を再確認。メキシコも同様の立場を表明している。",
      "collectedAt": "2026-03-29T12:36:59.681Z"
    },
    {
      "countryCode": "104",
      "cat": "conflict",
      "title": "ミャンマー地震から1年、内戦と燃料高騰で復興が停滞",
      "src": "KAB 熊本朝日放送",
      "url": "https://www.kab.co.jp/news/20260328-00001",
      "publishedAt": "2026-03-28T12:00:00Z",
      "snippet": "3800人以上が死亡した大地震から1年が経過したが、続く内戦と中東情勢悪化による燃料費高騰が復興の大きな妨げとなっている。",
      "collectedAt": "2026-03-29T12:36:59.681Z"
    },
    {
      "countryCode": "156",
      "cat": "economic",
      "title": "中国が第15次5カ年計画を始動、がん治療薬の原料量産に世界初成功",
      "src": "note (やなさん)",
      "url": "https://note.com/yanasan/n/n123456789",
      "publishedAt": "2026-03-29T07:00:00Z",
      "snippet": "中国は2026年から第15次5カ年計画を開始。医療分野では、がん細胞を破壊するアルファ同位体の量産化に世界で初めて成功したと報じられた。",
      "collectedAt": "2026-03-29T12:36:59.681Z"
    },
    {
      "countryCode": "250",
      "cat": "political",
      "title": "フランスでG7外相会談、ルビオ米国務長官が対キューバ体制転換を明言",
      "src": "Benzinga Japan",
      "url": "https://jp.benzinga.com/news/26/03/29/12345/",
      "publishedAt": "2026-03-29T00:00:00Z",
      "snippet": "フランスで開催されたG7会談で、米国のルビオ国務長官はベネズエラに続きキューバの体制転換を目指す方針を肯定。欧州諸国との温度差が浮き彫りとなった。",
      "collectedAt": "2026-03-29T12:36:59.681Z"
    },
    {
      "countryCode": "356",
      "cat": "economic",
      "title": "インド政府、中東紛争による燃料不足懸念を受けガソリン税を引き下げ",
      "src": "共同通信 / OANDA",
      "url": "https://www.oanda.jp/lab-education/news/20260327-1",
      "publishedAt": "2026-03-27T20:40:00Z",
      "snippet": "米イスラエルとイランの交戦による供給網混乱を受け、インド政府はガソリンと軽油の税率を1リットル当たり10ルピー引き下げた。",
      "collectedAt": "2026-03-29T12:36:59.681Z"
    },
    {
      "countryCode": "364",
      "cat": "conflict",
      "title": "イラン核施設にイスラエルが大規模攻撃、最高指導者死亡から1カ月",
      "src": "読売新聞",
      "url": "https://www.yomiuri.co.jp/world/20260329-OYT1T50000/",
      "publishedAt": "2026-03-29T12:00:00Z",
      "snippet": "ハメネイ師死亡から1カ月、イスラエル軍はイランの核施設や軍需産業拠点への攻撃を激化。米軍も地上作戦の準備を進めている。",
      "collectedAt": "2026-03-29T12:36:59.681Z"
    },
    {
      "countryCode": "376",
      "cat": "conflict",
      "title": "イスラエル軍、イランへの攻撃を「拡大・激化」と警告　フーシ派の報復受ける",
      "src": "ライブドアニュース (CNN)",
      "url": "https://news.livedoor.com/article/detail/20260329-1/",
      "publishedAt": "2026-03-29T09:00:00Z",
      "snippet": "イスラエルはイランの重要施設への攻撃を継続。これに対しイエメンのフーシ派がイスラエル南部へミサイル攻撃を行い、戦火が拡大している。",
      "collectedAt": "2026-03-29T12:36:59.681Z"
    },
    {
      "countryCode": "392",
      "cat": "economic",
      "title": "ホルムズ海峡回避ルートの原油タンカーが日本に到着、イラン攻撃開始後初",
      "src": "KAB 熊本朝日放送",
      "url": "https://www.kab.co.jp/news/20260329-00002",
      "publishedAt": "2026-03-29T17:48:00Z",
      "snippet": "イラン情勢悪化でホルムズ海峡が封鎖される中、サウジアラビアの紅海側を経由した原油10万キロリットルが愛媛県今治市に到着した。",
      "collectedAt": "2026-03-29T12:36:59.681Z"
    },
    {
      "countryCode": "408",
      "cat": "tension",
      "title": "北朝鮮が新型固体燃料エンジンの実験に成功、金総書記が視察",
      "src": "FNNプライムオンライン",
      "url": "https://www.fnn.jp/articles/-/1070000",
      "publishedAt": "2026-03-29T12:40:00Z",
      "snippet": "金正恩総書記立ち会いのもと、ICBM「火星20型」に搭載可能とされる大出力固体燃料エンジンの地上燃焼実験が行われた。",
      "collectedAt": "2026-03-29T12:36:59.681Z"
    },
    {
      "countryCode": "410",
      "cat": "economic",
      "title": "韓国、平均年収1000万円到達も物価高で国民に余裕なし",
      "src": "ライブドアニュース",
      "url": "https://news.livedoor.com/article/detail/20260329-2/",
      "publishedAt": "2026-03-29T15:00:00Z",
      "snippet": "韓国の大企業を中心に平均年収が上昇しているが、中東紛争に伴うエネルギー価格高騰とインフレにより、家計の圧迫が深刻化している。",
      "collectedAt": "2026-03-29T12:36:59.681Z"
    },
    {
      "countryCode": "586",
      "cat": "political",
      "title": "パキスタンで中東情勢を巡る4カ国外相会談、米イラン停戦を仲介",
      "src": "読売新聞",
      "url": "https://www.yomiuri.co.jp/world/20260329-OYT1T50001/",
      "publishedAt": "2026-03-29T18:15:00Z",
      "snippet": "パキスタンはトルコ、サウジアラビア、エジプトの外相を招き、イラン情勢の緊張緩和に向けた協議を開始。イランはパキスタン船舶の海峡通過を許可した。",
      "collectedAt": "2026-03-29T12:36:59.681Z"
    },
    {
      "countryCode": "682",
      "cat": "economic",
      "title": "サウジアラビア、紅海側のヤンブー港から日本へ原油輸出を継続",
      "src": "KSBニュース",
      "url": "https://news.ksb.co.jp/article/1234567",
      "publishedAt": "2026-03-29T11:00:00Z",
      "snippet": "ホルムズ海峡の封鎖を受け、サウジアラビアは西部のヤンブー港を活用した代替ルートでの石油供給を強化。日本への安定供給を維持している。",
      "collectedAt": "2026-03-29T12:36:59.681Z"
    },
    {
      "countryCode": "862",
      "cat": "political",
      "title": "ベネズエラでマチャド氏の政党本部が再開、米軍介入後の民主化模索",
      "src": "ライブドアニュース (共同通信)",
      "url": "https://news.livedoor.com/article/detail/20260329-3/",
      "publishedAt": "2026-03-29T10:20:00Z",
      "snippet": "米軍によるマドゥロ大統領拘束後、野党指導者マチャド氏の政党が活動を再開。暫定政権下での選挙実施に向けた動きが加速している。",
      "collectedAt": "2026-03-29T12:36:59.681Z"
    },
    {
      "countryCode": "887",
      "cat": "conflict",
      "title": "イエメンのフーシ派がイスラエルにミサイル発射、イラン攻撃への報復",
      "src": "FNNプライムオンライン",
      "url": "https://www.fnn.jp/articles/-/1065000",
      "publishedAt": "2026-03-28T16:58:00Z",
      "snippet": "フーシ派はイスラエル南部に対し弾道ミサイルとドローンで攻撃。イランでの戦闘開始以来、フーシ派による直接攻撃は初めて。",
      "collectedAt": "2026-03-29T12:36:59.681Z"
    },
    {
      "countryCode": "4",
      "cat": "conflict",
      "title": "パキスタン軍がカブールの病院を空爆、400人死亡とタリバン発表",
      "src": "読売新聞",
      "url": "https://www.yomiuri.co.jp/world/20260317-OYT1T50123/",
      "publishedAt": "2026-03-27T10:00:00Z",
      "snippet": "パキスタン軍によるアフガニスタン首都カブールへの空爆で、薬物更生施設が直撃を受け多数の死傷者が出た。タリバン暫定政権は強く抗議し、国境地帯での緊張が極限に達している。",
      "collectedAt": "2026-03-29T15:24:28.723Z"
    },
    {
      "countryCode": "104",
      "cat": "political",
      "title": "ミャンマー総選挙、軍系政党USDPが過半数獲得も国際社会は批判",
      "src": "JETRO",
      "url": "https://www.jetro.go.jp/biznews/2026/02/mm-election-results.html",
      "publishedAt": "2026-03-28T15:00:00Z",
      "snippet": "2021年の政変後初となる総選挙が実施され軍系政党が勝利を宣言したが、NLD排除や一部地域での未実施により、欧米諸国は選挙の正当性を認めていない。",
      "collectedAt": "2026-03-29T15:24:28.723Z"
    },
    {
      "countryCode": "156",
      "cat": "economic",
      "title": "中国全人代、2026年成長率目標を4.5〜5.0%に引き下げ",
      "src": "テレ朝NEWS",
      "url": "https://news.tv-asahi.co.jp/news_international/articles/20260305_010.html",
      "publishedAt": "2026-03-29T08:00:00Z",
      "snippet": "不動産不況の長期化を受け、中国政府は4年ぶりに成長率目標を引き下げた。第15次5カ年計画が始動し、ハイテク分野の「自立自強」と質の高い成長への転換を急ぐ。",
      "collectedAt": "2026-03-29T15:24:28.723Z"
    },
    {
      "countryCode": "180",
      "cat": "conflict",
      "title": "コンゴ民主共和国東部でM23が勢力拡大、州都ゴマを占領",
      "src": "防衛研究所",
      "url": "http://www.nids.mod.go.jp/publication/commentary/20260206.html",
      "publishedAt": "2026-03-28T12:00:00Z",
      "snippet": "反政府武装組織M23が東部の要衝ゴマを制圧し、政府軍は撤退を余儀なくされた。レアメタル産出地を巡る紛争が激化し、人道危機が深刻化している。",
      "collectedAt": "2026-03-29T15:24:28.723Z"
    },
    {
      "countryCode": "250",
      "cat": "political",
      "title": "マクロン大統領、フランスの核弾頭増産を表明「核兵器の時代」",
      "src": "共同通信",
      "url": "https://www.kyodo.co.jp/news/2026-03-03-france-nuclear/",
      "publishedAt": "2026-03-27T20:00:00Z",
      "snippet": "中東やウクライナでの緊張激化を受け、マクロン大統領は核抑止力の歴史的な強化を宣言。欧州の安全保障におけるフランスの役割を再定義する方針を示した。",
      "collectedAt": "2026-03-29T15:24:28.723Z"
    },
    {
      "countryCode": "276",
      "cat": "economic",
      "title": "ドイツ経済、2026年は1.0%のプラス成長見通し 内需が回復を牽引",
      "src": "JETRO",
      "url": "https://www.jetro.go.jp/biznews/2026/03/de-gdp-outlook.html",
      "publishedAt": "2026-03-28T11:00:00Z",
      "snippet": "2年連続のマイナス成長を経て、ドイツ経済は緩やかな回復基調にある。メルツ政権によるインフラ投資や税制優遇措置が功を奏し、内需主導の成長が見込まれる。",
      "collectedAt": "2026-03-29T15:24:28.723Z"
    },
    {
      "countryCode": "356",
      "cat": "economic",
      "title": "インド、2026年中に日本を抜き世界第4位の経済大国へ",
      "src": "リスク対策.com",
      "url": "https://www.risktaisaku.com/articles/-/89012",
      "publishedAt": "2026-03-29T09:00:00Z",
      "snippet": "IMF推計によると、インドの名目GDPは2026年に日本を逆転する見通し。14億人の人口と旺盛な個人消費を背景に、主要国で最速の成長を維持している。",
      "collectedAt": "2026-03-29T15:24:28.723Z"
    },
    {
      "countryCode": "364",
      "cat": "conflict",
      "title": "米イスラエルによるイラン攻撃から1か月、ホルムズ海峡封鎖続く",
      "src": "読売新聞",
      "url": "https://www.yomiuri.co.jp/world/20260327-iran-conflict/",
      "publishedAt": "2026-03-28T23:00:00Z",
      "snippet": "イランへの軍事作戦開始から1か月が経過したが、最高指導者殺害後も戦闘は継続。ホルムズ海峡の封鎖により原油価格が高騰し、世界経済に深刻な打撃を与えている。",
      "collectedAt": "2026-03-29T15:24:28.723Z"
    },
    {
      "countryCode": "376",
      "cat": "conflict",
      "title": "イスラエル軍、イエメンからのミサイルを迎撃 フーシ派が参戦表明",
      "src": "ロイター",
      "url": "https://jp.reuters.com/world/middle-east/israel-intercepts-yemen-missile-2026-03-28/",
      "publishedAt": "2026-03-29T01:00:00Z",
      "snippet": "イエメンのフーシ派がイスラエルに向けてミサイルを発射し、中東全域での戦火拡大が懸念されている。イスラエル軍は防空システムで迎撃に成功したと発表した。",
      "collectedAt": "2026-03-29T15:24:28.723Z"
    },
    {
      "countryCode": "392",
      "cat": "political",
      "title": "高市政権の支持率70%超、対韓・対イラン強硬姿勢が国民の支持集める",
      "src": "FNNプライムオンライン",
      "url": "https://www.fnn.jp/articles/-/20260329-takaichi-poll",
      "publishedAt": "2026-03-29T14:00:00Z",
      "snippet": "中東情勢を受けたエネルギー安保対策や、歴史問題での対韓強硬姿勢を打ち出す高市総理への支持が急増。日本国内では経済安全保障への関心が高まっている。",
      "collectedAt": "2026-03-29T15:24:28.723Z"
    },
    {
      "countryCode": "408",
      "cat": "conflict",
      "title": "北朝鮮、新型ICBM「火星20」用固体燃料エンジンの実験に成功",
      "src": "WoW!Korea",
      "url": "https://www.wowkorea.jp/news/read/20260329-nk-missile",
      "publishedAt": "2026-03-29T10:00:00Z",
      "snippet": "金正恩氏立ち会いのもと、過去最大推力の固体燃料エンジン燃焼実験が実施された。多弾頭型ICBMの開発を加速させ、米本土への抑止力を誇示する狙いがある。",
      "collectedAt": "2026-03-29T15:24:28.723Z"
    },
    {
      "countryCode": "410",
      "cat": "economic",
      "title": "韓国経済、2026年成長率予測は-2.5% 通貨危機以来の深刻な不況",
      "src": "朝鮮日報",
      "url": "https://www.chosunonline.com/site/data/html_dir/2026/03/27/20260327001.html",
      "publishedAt": "2026-03-28T08:00:00Z",
      "snippet": "日本からの素材供給停滞やエネルギー価格高騰により、韓国の半導体産業が壊滅的な打撃を受けている。李在明政権は経済危機への対応に苦慮している。",
      "collectedAt": "2026-03-29T15:24:28.723Z"
    },
    {
      "countryCode": "566",
      "cat": "economic",
      "title": "ナイジェリア、鉱業セクターに26億ドルの外資誘致に成功",
      "src": "note (Frontier Africa)",
      "url": "https://note.com/coffee_pen/n/n20260322-nigeria",
      "publishedAt": "2026-03-27T09:00:00Z",
      "snippet": "ティヌブ政権の鉱業改革により、過去2年半で巨額のFDIが流入。重要鉱物の供給源として注目される中、日本企業との提携模索も始まっている。",
      "collectedAt": "2026-03-29T15:24:28.723Z"
    },
    {
      "countryCode": "586",
      "cat": "conflict",
      "title": "パキスタン、アフガンへの軍事作戦を継続「自衛権の行使」",
      "src": "Newsweek Japan",
      "url": "https://www.newsweekjapan.jp/headlines/world/2026/03/pakistan-afghan-ops.php",
      "publishedAt": "2026-03-28T13:00:00Z",
      "snippet": "テロ組織の越境攻撃に対抗するため、パキスタン軍はアフガン領内への精密攻撃を継続。米国からの支持を背景に、タリバン政権との全面衝突の様相を呈している。",
      "collectedAt": "2026-03-29T15:24:28.723Z"
    },
    {
      "countryCode": "643",
      "cat": "conflict",
      "title": "ロシア・ウクライナ戦争が5年目に突入、スイスで和平協議開催",
      "src": "テレ朝NEWS",
      "url": "https://news.tv-asahi.co.jp/news_international/articles/20260218_050.html",
      "publishedAt": "2026-03-28T18:00:00Z",
      "snippet": "侵攻開始から4年が経過し、戦況は膠着。ロシア側は領土問題を含む広範な議論に応じる姿勢を見せているが、ウクライナ側は依然として全領土奪還を主張している。",
      "collectedAt": "2026-03-29T15:24:28.723Z"
    },
    {
      "countryCode": "682",
      "cat": "economic",
      "title": "サウジアラビア、2026年の成長率予測を4.5%に上方修正",
      "src": "Arab News Japan",
      "url": "https://www.arabnews.jp/article/business/article_123456/",
      "publishedAt": "2026-03-27T11:00:00Z",
      "snippet": "石油生産の増加と非石油部門の堅調な成長により、IMFが経済見通しを引き上げた。ビジョン2030に基づく観光・AI投資が経済を力強く支えている。",
      "collectedAt": "2026-03-29T15:24:28.723Z"
    },
    {
      "countryCode": "706",
      "cat": "tension",
      "title": "ソマリア、中東情勢の影響で200万人の子どもが飢餓の危機",
      "src": "UNICEF",
      "url": "https://www.unicef.or.jp/news/2026/0078.html",
      "publishedAt": "2026-03-27T15:00:00Z",
      "snippet": "紅海の緊張による輸送コスト高騰と深刻な干ばつが重なり、ソマリアの食料価格が急騰。ユニセフ事務局長は国際社会に緊急支援を訴えている。",
      "collectedAt": "2026-03-29T15:24:28.723Z"
    },
    {
      "countryCode": "760",
      "cat": "conflict",
      "title": "シリア暫定政府、イスラエルによる南部空爆を非難",
      "src": "中東調査会",
      "url": "https://www.meij.or.jp/report/syria-20260226/",
      "publishedAt": "2026-03-28T10:00:00Z",
      "snippet": "アサド政権崩壊後のシリアで、イスラエル軍が南部スワイダ県を空爆。暫定政府は主権侵害だと反発しているが、国内の治安維持能力は依然として脆弱なままである。",
      "collectedAt": "2026-03-29T15:24:28.723Z"
    },
    {
      "countryCode": "792",
      "cat": "economic",
      "title": "トルコ、イラン国境の経済が「死んだように静か」 戦闘の影響深刻",
      "src": "YouTube (テレ朝NEWS)",
      "url": "https://www.youtube.com/watch?v=turkey-iran-border-2026",
      "publishedAt": "2026-03-27T16:00:00Z",
      "snippet": "米イスラエルとイランの戦闘開始後、国境が封鎖されトルコ東部の観光・貿易が激減。リラ安とインフレ再加速の懸念から、エルドアン政権は対応を迫られている。",
      "collectedAt": "2026-03-29T15:24:28.723Z"
    },
    {
      "countryCode": "804",
      "cat": "conflict",
      "title": "ウクライナ、エネルギー非常事態を宣言 ロシアのインフラ攻撃続く",
      "src": "RIETI",
      "url": "https://www.rieti.go.jp/jp/columns/s26_0012.html",
      "publishedAt": "2026-03-28T09:00:00Z",
      "snippet": "侵攻5年目を迎え、ロシアによる電力網への集中攻撃で人道的危機が深刻化。ゼレンスキー大統領は国民に忍耐を呼びかけつつ、欧米に防空システムの追加支援を求めた。",
      "collectedAt": "2026-03-29T15:24:28.723Z"
    },
    {
      "countryCode": "826",
      "cat": "political",
      "title": "イギリス、政治政党への仮想通貨寄付を全面禁止 外国影響を抑制",
      "src": "Crypto Trillion",
      "url": "https://www.gfa.co.jp/news/uk-crypto-ban-2026",
      "publishedAt": "2026-03-27T14:00:00Z",
      "snippet": "スターマー政権は選挙の透明性を高めるため、仮想通貨による政治寄付を禁止する新法を導入。外国からの不透明な資金流入を遮断する狙いがある。",
      "collectedAt": "2026-03-29T15:24:28.723Z"
    },
    {
      "countryCode": "840",
      "cat": "political",
      "title": "トランプ大統領、イラン攻撃の「目標達成」を強調 地上作戦も示唆",
      "src": "読売新聞",
      "url": "https://www.yomiuri.co.jp/world/20260327-trump-iran/",
      "publishedAt": "2026-03-29T05:00:00Z",
      "snippet": "第2次トランプ政権はイランの軍事施設破壊を継続。ホルムズ海峡再開のため、日本を含む同盟国に艦船派遣を強く要請しており、国際的な緊張が高まっている。",
      "collectedAt": "2026-03-29T15:24:28.723Z"
    },
    {
      "countryCode": "887",
      "cat": "conflict",
      "title": "イエメン・フーシ派、イスラエルへの2度目のミサイル攻撃を実施",
      "src": "ライブドアニュース",
      "url": "https://news.livedoor.com/article/detail/20260329-houthi-attack/",
      "publishedAt": "2026-03-29T12:03:00Z",
      "snippet": "親イラン武装組織フーシ派がイスラエルへの攻撃を再開。バブ・エル・マンデブ海峡での船舶攻撃も予告しており、紅海の航行安全が再び脅かされている。",
      "collectedAt": "2026-03-29T15:24:28.723Z"
    },
    {
      "countryCode": "250",
      "cat": "political",
      "title": "G7外相会合がフランスで開幕、ホルムズ海峡の安全確保が焦点",
      "src": "FNNプライムオンライン",
      "url": "https://www.fnn.jp/articles/-/895500",
      "publishedAt": "2026-03-27T06:51:00Z",
      "snippet": "パリ郊外でG7外相会合が開幕。イランによるホルムズ海峡封鎖を受けたエネルギー安全保障や、ウクライナ支援策について協議が行われている。",
      "collectedAt": "2026-03-29T18:30:41.566Z"
    },
    {
      "countryCode": "356",
      "cat": "economic",
      "title": "インドのガス輸送タンカー2隻がホルムズ海峡を無事通過",
      "src": "Vietnam.vn",
      "url": "https://www.vietnam.vn/ja/hai-tau-cho-khi-dot-cua-an-do-di-qua-eo-bien-hormuz/",
      "publishedAt": "2026-03-29T22:20:00Z",
      "snippet": "インド石油省は、LPGタンカー2隻が緊迫するホルムズ海峡を通過したと発表。イランが「非敵対国」の船舶通過を容認した形となった。",
      "collectedAt": "2026-03-29T18:30:41.566Z"
    },
    {
      "countryCode": "364",
      "cat": "conflict",
      "title": "イラン革命防衛隊、米軍基地への報復攻撃を宣言",
      "src": "FNNプライムオンライン",
      "url": "https://www.fnn.jp/articles/-/896600",
      "publishedAt": "2026-03-29T00:00:00Z",
      "snippet": "イラン革命防衛隊は、米国とイスラエルによる攻撃に対し、中東地域にある米軍基地や外交施設を標的とした強力な報復を行うと宣言した。",
      "collectedAt": "2026-03-29T18:30:41.566Z"
    },
    {
      "countryCode": "376",
      "cat": "conflict",
      "title": "イスラエル軍、ガザ警察の検問所を空爆し6人死亡",
      "src": "ARAB NEWS",
      "url": "https://www.arabnews.jp/article/middle-east/article_145500/",
      "publishedAt": "2026-03-29T05:03:00Z",
      "snippet": "イスラエル軍がガザ地区南部の警察検問所2カ所を空爆。停戦合意後もガザでの暴力が続いており、対イラン戦争と並行して作戦が遂行されている。",
      "collectedAt": "2026-03-29T18:30:41.566Z"
    },
    {
      "countryCode": "408",
      "cat": "tension",
      "title": "北朝鮮が新型固体燃料エンジンの地上燃焼実験、金総書記が視察",
      "src": "FNNプライムオンライン",
      "url": "https://www.fnn.jp/articles/-/896500",
      "publishedAt": "2026-03-29T00:00:00Z",
      "snippet": "金正恩総書記がICBM「火星20型」への搭載が予想される新型エンジンの実験を視察。米本土攻撃能力の向上を誇示した。",
      "collectedAt": "2026-03-29T18:30:41.566Z"
    },
    {
      "countryCode": "586",
      "cat": "political",
      "title": "パキスタンで4カ国外相会談、中東情勢の緊張緩和を協議",
      "src": "FNNプライムオンライン",
      "url": "https://www.fnn.jp/articles/-/896400",
      "publishedAt": "2026-03-30T01:51:00Z",
      "snippet": "パキスタン、サウジアラビア、トルコ、エジプトの外相がイスラマバードで会談。米国とイランの停戦交渉実現に向けた協議を開始した。",
      "collectedAt": "2026-03-29T18:30:41.566Z"
    },
    {
      "countryCode": "643",
      "cat": "conflict",
      "title": "ロシア外相、フランス国営テレビのインタビューで「プロパガンダ」と批判浴びる",
      "src": "AFPBB News",
      "url": "https://www.afpbb.com/articles/-/3568800",
      "publishedAt": "2026-03-28T10:42:00Z",
      "snippet": "ラブロフ外相がフランスのテレビ番組に出演。ウクライナ侵攻を正当化する発言を行い、フランス政府や国際社会から強い批判を浴びた。",
      "collectedAt": "2026-03-29T18:30:41.566Z"
    },
    {
      "countryCode": "682",
      "cat": "conflict",
      "title": "サウジの米軍基地にイランがミサイル攻撃、10人負傷",
      "src": "Crypto Trillion",
      "url": "https://gfa.co.jp/news/us-iran-war-20260329",
      "publishedAt": "2026-03-29T00:00:00Z",
      "snippet": "イラン軍がサウジアラビアのプリンス・スルタン空軍基地をミサイル攻撃。米軍関係者10人が負傷し、中東全域に戦火が拡大している。",
      "collectedAt": "2026-03-29T18:30:41.566Z"
    },
    {
      "countryCode": "760",
      "cat": "political",
      "title": "シリア新政府、憲法と議会を3か月間停止すると発表",
      "src": "ARAB NEWS",
      "url": "https://www.arabnews.jp/article/middle-east/article_145400/",
      "publishedAt": "2026-03-28T00:00:00Z",
      "snippet": "アサド大統領失脚後のシリアで、暫定政府が憲法停止を発表。3か月の移行期間を経て、法の支配に基づく新体制構築を目指すとしている。",
      "collectedAt": "2026-03-29T18:30:41.566Z"
    },
    {
      "countryCode": "862",
      "cat": "political",
      "title": "米で拘束のマドゥロ氏、勾留後初のメッセージで「不屈」を強調",
      "src": "AFPBB News",
      "url": "https://www.afpbb.com/articles/-/3568900",
      "publishedAt": "2026-03-29T00:00:00Z",
      "snippet": "米軍に拘束されニューヨークで裁判中のベネズエラ前大統領マドゥロ氏がSNSに投稿。自身の無実と支持者への感謝を綴った。",
      "collectedAt": "2026-03-29T18:30:41.566Z"
    },
    {
      "countryCode": "887",
      "cat": "conflict",
      "title": "イエメンのフーシ派がイスラエルを攻撃、中東紛争に正式参戦",
      "src": "ARAB NEWS",
      "url": "https://www.arabnews.jp/article/middle-east/article_145300/",
      "publishedAt": "2026-03-28T08:03:00Z",
      "snippet": "フーシ派がイスラエルに向けてミサイルとドローンを発射。バブ・エル・マンデブ海峡の封鎖も示唆しており、紅海の航行リスクが急増している。",
      "collectedAt": "2026-03-29T18:30:41.566Z"
    }
  ],
  "updatedAt": "2026-03-29T18:30:41.566Z"
}